RTL/Day05/counter_param.v
module counter_param
#(
    parameter WIDTH = 8
)
(
    input clk,
    input reset,
    input enable,
    output reg [WIDTH-1:0] count
);


always @(posedge clk)
begin

    if(reset)
        count <= 0;

    else if(enable)
        count <= count + 1;
    else
        count <= count;
end


endmodule

Testbench/Day05/counter_param_tb.v
`timescale 1ns/1ps

module counter_param_tb;

    reg clk;
    reg reset;
    reg enable;

    wire [7:0] count;


    // DUT (Device Under Test)
    counter_param #(
        .WIDTH(8)
    ) uut (
        .clk(clk),
        .reset(reset),
        .enable(enable),
        .count(count)
    );


    // Clock generation
    always #5 clk = ~clk;


    // Test sequence
    initial
    begin

        // Generate waveform
        $dumpfile("Simulation/Day05/counter_param.vcd");
        $dumpvars(0, counter_param_tb);


        // Initial state
        clk = 0;
        reset = 1;
        enable = 0;


        // Test reset
        #10;
        reset = 0;


        // Test counting
        enable = 1;

        #50;


        // Test hold
        enable = 0;

        #30;


        // Test reset again
        reset = 1;

        #10;


        reset = 0;

        #20;


        $finish;

    end


endmodule

Simulation/Day05/counter_param.vcd
$date
	Wed Jul 22 23:09:50 2026
$end
$version
	Icarus Verilog
$end
$timescale
	1ps
$end
$scope module counter_param_tb $end
$var wire 8 ! count [7:0] $end
$var reg 1 " clk $end
$var reg 1 # enable $end
$var reg 1 $ reset $end
$scope module uut $end
$var wire 1 " clk $end
$var wire 1 # enable $end
$var wire 1 $ reset $end
$var parameter 32 % WIDTH $end
$var reg 8 & count [7:0] $end
$upscope $end
$upscope $end
$enddefinitions $end
$comment Show the parameter values. $end
$dumpall
b1000 %
$end
#0
$dumpvars
bx &
1$
0#
0"
bx !
$end
#5000
b0 !
b0 &
1"
#10000
0"
1#
0$
#15000
b1 !
b1 &
1"
#20000
0"
#25000
b10 !
b10 &
1"
#30000
0"
#35000
b11 !
b11 &
1"
#40000
0"
#45000
b100 !
b100 &
1"
#50000
0"
#55000
b101 !
b101 &
1"
#60000
0"
0#
#65000
1"
#70000
0"
#75000
1"
#80000
0"
#85000
1"
#90000
0"
1$
#95000
b0 !
b0 &
1"
#100000
0"
0$
