RTL/Day04/traffic_light_fsm.v
module traffic_light_fsm(

    input  wire clk,
    input  wire rst_n,

    output reg red,
    output reg yellow,
    output reg green

);


    //--------------------------------
    // State Encoding
    //--------------------------------

    localparam RED    = 2'b00;
    localparam GREEN  = 2'b01;
    localparam YELLOW = 2'b10;


    //--------------------------------
    // State Register
    //--------------------------------

    reg [1:0] current_state;
    reg [1:0] next_state;


    //--------------------------------
    // State Update
    //--------------------------------

    always @(posedge clk) begin

        if(!rst_n)

            current_state <= RED;

        else

            current_state <= next_state;

    end



    //--------------------------------
    // Next State Logic
    //--------------------------------

    always @(*) begin

        case(current_state)

            RED:
                next_state = GREEN;


            GREEN:
                next_state = YELLOW;


            YELLOW:
                next_state = RED;


            default:
                next_state = RED;


        endcase

    end



    //--------------------------------
    // Output Logic
    //--------------------------------

    always @(*) begin


        red    = 1'b0;
        yellow = 1'b0;
        green  = 1'b0;


        case(current_state)


            RED:
                red = 1'b1;


            GREEN:
                green = 1'b1;


            YELLOW:
                yellow = 1'b1;


            default:
            begin

                red    = 1'b0;
                yellow = 1'b0;
                green  = 1'b0;

            end


        endcase


    end


endmodule

Testbench/Day04/traffic_light_tb.v
`timescale 1ns/1ps


module traffic_light_tb;


    //--------------------------------
    // Testbench Signals
    //--------------------------------

    reg clk;
    reg rst_n;


    wire red;
    wire yellow;
    wire green;



    //--------------------------------
    // DUT Instance
    //--------------------------------

    traffic_light_fsm dut (

        .clk(clk),
        .rst_n(rst_n),

        .red(red),
        .yellow(yellow),
        .green(green)

    );



    //--------------------------------
    // Clock Generation
    //--------------------------------

    always #5 clk = ~clk;



    //--------------------------------
    // Simulation
    //--------------------------------

    initial begin


        // waveform
        $dumpfile("traffic_light.vcd");
        $dumpvars(0, traffic_light_tb);



        // initial value

        clk = 0;

        rst_n = 0;



        // reset period

        #20;


        rst_n = 1;



        // run simulation

        #100;



        $finish;


    end



endmodule

traffic_light.vcd
$date
	Mon Jul 20 17:43:42 2026
$end
$version
	Icarus Verilog
$end
$timescale
	1ps
$end
$scope module traffic_light_tb $end
$var wire 1 ! yellow $end
$var wire 1 " red $end
$var wire 1 # green $end
$var reg 1 $ clk $end
$var reg 1 % rst_n $end
$scope module dut $end
$var wire 1 $ clk $end
$var wire 1 % rst_n $end
$var parameter 2 & GREEN $end
$var parameter 2 ' RED $end
$var parameter 2 ( YELLOW $end
$var reg 2 ) current_state [1:0] $end
$var reg 1 # green $end
$var reg 2 * next_state [1:0] $end
$var reg 1 " red $end
$var reg 1 ! yellow $end
$upscope $end
$upscope $end
$enddefinitions $end
$comment Show the parameter values. $end
$dumpall
b10 (
b0 '
b1 &
$end
#0
$dumpvars
bx *
bx )
0%
0$
x#
x"
x!
$end
#5000
0#
0!
1"
b1 *
b0 )
1$
#10000
0$
#15000
1$
#20000
0$
1%
#25000
b10 *
1#
0"
b1 )
1$
#30000
0$
#35000
1!
0#
b0 *
b10 )
1$
#40000
0$
#45000
b1 *
1"
0!
b0 )
1$
#50000
0$
#55000
1#
0"
b10 *
b1 )
1$
#60000
0$
#65000
b0 *
1!
0#
b10 )
1$
#70000
0$
#75000
1"
0!
b1 *
b0 )
1$
#80000
0$
#85000
b10 *
1#
0"
b1 )
1$
#90000
0$
#95000
1!
0#
b0 *
b10 )
1$
#100000
0$
#105000
b1 *
1"
0!
b0 )
1$
#110000
0$
#115000
1#
0"
b10 *
b1 )
1$
