RTL/Day03/dff.v
module dff(
    input clk,
    input d,
    output reg q
);

always @(posedge clk)
begin
    q <= d;
end

endmodule

Testbench/Day03/dff_tb.v
`timescale 1ns/1ps

module dff_tb;

reg clk;
reg d;

wire q;


dff uut(
    .clk(clk),
    .d(d),
    .q(q)
);


// Clock generation
initial begin
    clk = 0;

    forever #5 clk = ~clk;

end


// Test stimulus
initial begin

    $dumpfile("dff.vcd");
    $dumpvars(0,dff_tb);


    d = 0;


    #12;

    d = 1;


    #10;

    d = 0;


    #10;

    d = 1;


    #10;


    $finish;

end


endmodule

Simulation/Day03/dff/dff.vcd
$date
	Sat Jul 18 22:24:22 2026
$end
$version
	Icarus Verilog
$end
$timescale
	1ps
$end
$scope module dff_tb $end
$var wire 1 ! q $end
$var reg 1 " clk $end
$var reg 1 # d $end
$scope module uut $end
$var wire 1 " clk $end
$var wire 1 # d $end
$var reg 1 ! q $end
$upscope $end
$upscope $end
$enddefinitions $end
$comment Show the parameter values. $end
$dumpall
$end
#0
$dumpvars
0#
0"
x!
$end
#5000
0!
1"
#10000
0"
#12000
1#
#15000
1!
1"
#20000
0"
#22000
0#
#25000
0!
1"
#30000
0"
#32000
1#
#35000
1!
1"
