RTL/Day17/matmul_2x2.v
`timescale 1ns/1ps

//==========================================================
// Day 17 : Parallel 2x2 Matrix Multiply
//==========================================================
//
// Four MAC units compute all four output elements of
// C = A x B simultaneously (spatial parallelism).
//
//   C[i][j] = A[i][0]*B[0][j] + A[i][1]*B[1][j]
//
// Pipeline:
//   MAC1 : each accumulator adds the k=0 product
//   MAC2 : each accumulator adds the k=1 product -> result
//
// Latency from start sampling to done:
//   2 clock cycles (MAC1 + MAC2), plus 1 cycle to clear.
//
// Compared with Day16 serial NPU (~88 cycles for the whole
// 2x2 matrix), this parallel design finishes in ~3 cycles.
// The cost is 4x more hardware (4 multipliers + 4 adders).
//==========================================================

module matmul_2x2 #(

    parameter DATA_WIDTH = 8,
    parameter ACC_WIDTH  = 32

)(

    input  wire clk,
    input  wire reset,
    input  wire start,

    //--------------------------------------------------
    // A matrix (row-major), 2x2
    //--------------------------------------------------

    input  wire signed [DATA_WIDTH-1:0] a00, a01,
    input  wire signed [DATA_WIDTH-1:0] a10, a11,

    //--------------------------------------------------
    // B matrix (row-major), 2x2
    //--------------------------------------------------

    input  wire signed [DATA_WIDTH-1:0] b00, b01,
    input  wire signed [DATA_WIDTH-1:0] b10, b11,

    //--------------------------------------------------
    // C matrix = A x B, 2x2
    //--------------------------------------------------

    output reg  signed [ACC_WIDTH-1:0] c00, c01,
    output reg  signed [ACC_WIDTH-1:0] c10, c11,

    output reg  done

);

    //--------------------------------------------------
    // FSM state encoding
    //--------------------------------------------------

    localparam S_IDLE = 2'd0;  // wait for start
    localparam S_MAC1 = 2'd1;  // first  product (k=0)
    localparam S_MAC2 = 2'd2;  // second product (k=1) -> result

    reg [1:0] state;

    //--------------------------------------------------
    // 8-bit x 8-bit signed products (16-bit wide)
    //
    // p0_* : k=0 term  = A[i][0] * B[0][j]
    // p1_* : k=1 term  = A[i][1] * B[1][j]
    //--------------------------------------------------

    wire signed [(2*DATA_WIDTH)-1:0] p0_c00 = a00 * b00;
    wire signed [(2*DATA_WIDTH)-1:0] p0_c01 = a00 * b01;
    wire signed [(2*DATA_WIDTH)-1:0] p0_c10 = a10 * b00;
    wire signed [(2*DATA_WIDTH)-1:0] p0_c11 = a10 * b01;

    wire signed [(2*DATA_WIDTH)-1:0] p1_c00 = a01 * b10;
    wire signed [(2*DATA_WIDTH)-1:0] p1_c01 = a01 * b11;
    wire signed [(2*DATA_WIDTH)-1:0] p1_c10 = a11 * b10;
    wire signed [(2*DATA_WIDTH)-1:0] p1_c11 = a11 * b11;

    //--------------------------------------------------
    // Four independent accumulators (one per output)
    //--------------------------------------------------

    reg signed [ACC_WIDTH-1:0] acc00, acc01, acc10, acc11;

    //--------------------------------------------------
    // Sequential control + datapath
    //--------------------------------------------------

    always @(posedge clk) begin

        if (reset) begin

            state <= S_IDLE;

            acc00 <= {ACC_WIDTH{1'b0}};
            acc01 <= {ACC_WIDTH{1'b0}};
            acc10 <= {ACC_WIDTH{1'b0}};
            acc11 <= {ACC_WIDTH{1'b0}};

            c00   <= {ACC_WIDTH{1'b0}};
            c01   <= {ACC_WIDTH{1'b0}};
            c10   <= {ACC_WIDTH{1'b0}};
            c11   <= {ACC_WIDTH{1'b0}};

            done  <= 1'b0;

        end
        else begin

            // one-clock completion pulse
            done <= 1'b0;

            case (state)

                //----------------------------------------
                // Wait for start, then clear all 4 MACs
                //----------------------------------------

                S_IDLE: begin

                    if (start) begin

                        acc00 <= {ACC_WIDTH{1'b0}};
                        acc01 <= {ACC_WIDTH{1'b0}};
                        acc10 <= {ACC_WIDTH{1'b0}};
                        acc11 <= {ACC_WIDTH{1'b0}};

                        state <= S_MAC1;

                    end

                end

                //----------------------------------------
                // MAC1 : add the k=0 products
                //----------------------------------------

                S_MAC1: begin

                    acc00 <= acc00 + p0_c00;
                    acc01 <= acc01 + p0_c01;
                    acc10 <= acc10 + p0_c10;
                    acc11 <= acc11 + p0_c11;

                    state <= S_MAC2;

                end

                //----------------------------------------
                // MAC2 : add the k=1 products, capture result
                //
                // Non-blocking: acc on the right side is the
                // MAC1 value, so acc + p1 = final dot product.
                //----------------------------------------

                S_MAC2: begin

                    acc00 <= acc00 + p1_c00;
                    c00   <= acc00 + p1_c00;

                    acc01 <= acc01 + p1_c01;
                    c01   <= acc01 + p1_c01;

                    acc10 <= acc10 + p1_c10;
                    c10   <= acc10 + p1_c10;

                    acc11 <= acc11 + p1_c11;
                    c11   <= acc11 + p1_c11;

                    done  <= 1'b1;

                    state <= S_IDLE;

                end

                default: begin

                    state <= S_IDLE;

                end

            endcase

        end

    end

endmodule

Testbench/Day17/matmul_2x2_tb.v
`timescale 1ns/1ps

//==========================================================
// Day 17 : Parallel 2x2 Matrix Multiply - Testbench
//==========================================================
//
// Test 1: A=[1 2;3 4]  B=[5 6;7 8]   -> C=[19 22;43 50]
// Test 2: A=[-1 2;3 -4] B=[2 -1;0 3] -> C=[-2 7;6 -15]
//
// Also measures latency (cycles) from start to done, and
// compares it with Day16 serial execution (~88 cycles).
//==========================================================

module matmul_2x2_tb;

    localparam DATA_WIDTH = 8;
    localparam ACC_WIDTH  = 32;

    //--------------------------------------------------
    // Clock and reset
    //--------------------------------------------------

    reg clk;
    reg reset;
    reg start;

    //--------------------------------------------------
    // Matrix inputs
    //--------------------------------------------------

    reg signed [DATA_WIDTH-1:0] a00, a01, a10, a11;
    reg signed [DATA_WIDTH-1:0] b00, b01, b10, b11;

    //--------------------------------------------------
    // Result outputs
    //--------------------------------------------------

    wire signed [ACC_WIDTH-1:0] c00, c01, c10, c11;
    wire done;

    //--------------------------------------------------
    // Latency measurement
    //--------------------------------------------------

    reg [31:0] cycle;
    reg [31:0] start_cycle;
    reg [31:0] done_cycle;
    reg [31:0] latency;
    reg [31:0] latency1;
    reg [31:0] latency2;

    //--------------------------------------------------
    // Pass/fail counters
    //--------------------------------------------------

    integer pass_count;
    integer fail_count;

    //--------------------------------------------------
    // DUT : the parallel matrix multiplier
    //--------------------------------------------------

    matmul_2x2 #(

        .DATA_WIDTH(DATA_WIDTH),
        .ACC_WIDTH(ACC_WIDTH)

    ) dut (

        .clk(clk),
        .reset(reset),
        .start(start),

        .a00(a00), .a01(a01), .a10(a10), .a11(a11),

        .b00(b00), .b01(b01), .b10(b10), .b11(b11),

        .c00(c00), .c01(c01), .c10(c10), .c11(c11),

        .done(done)

    );

    //--------------------------------------------------
    // Clock generation : 10 ns period
    //--------------------------------------------------

    initial begin

        clk = 1'b0;

        forever #5 clk = ~clk;

    end

    //--------------------------------------------------
    // Cycle counter
    //--------------------------------------------------

    always @(posedge clk) cycle <= cycle + 1'b1;

    //--------------------------------------------------
    // Drive one matrix multiply and measure latency
    //--------------------------------------------------

    task automatic do_matmul (

        input signed [DATA_WIDTH-1:0] pa00, pa01, pa10, pa11,
        input signed [DATA_WIDTH-1:0] pb00, pb01, pb10, pb11,

        input [3:0] test_id

    );

        begin

            @(negedge clk);

            a00 = pa00; a01 = pa01; a10 = pa10; a11 = pa11;
            b00 = pb00; b01 = pb01; b10 = pb10; b11 = pb11;

            start = 1'b1;

            @(negedge clk);

            start = 1'b0;

            @(posedge clk);       // DUT samples start here
            start_cycle = cycle;

            @(posedge done);      // completion pulse
            done_cycle  = cycle;

            latency = done_cycle - start_cycle;

            $display("");
            $display("Test %0d:", test_id);
            $display("  A = [%0d %0d]     B = [%0d %0d]",
                a00, a01, b00, b01);
            $display("      [%0d %0d]         [%0d %0d]",
                a10, a11, b10, b11);
            $display("  C = [%0d %0d]", c00, c01);
            $display("      [%0d %0d]", c10, c11);
            $display("  latency = %0d cycles", latency);

        end

    endtask

    //--------------------------------------------------
    // Check helper
    //--------------------------------------------------

    task automatic check_matrix (

        input signed [ACC_WIDTH-1:0] e00, e01, e10, e11,
        input [3:0] test_id

    );

        begin

            if (
                c00 === e00 &&
                c01 === e01 &&
                c10 === e10 &&
                c11 === e11
            ) begin

                $display("  TEST%0d PASS : C = [%0d %0d; %0d %0d]",
                    test_id, e00, e01, e10, e11);

                pass_count = pass_count + 1;

            end
            else begin

                $display("  TEST%0d FAIL : got [%0d %0d; %0d %0d], expected [%0d %0d; %0d %0d]",
                    test_id, c00, c01, c10, c11, e00, e01, e10, e11);

                fail_count = fail_count + 1;

            end

        end

    endtask
    //--------------------------------------------------
    // Main test sequence
    //--------------------------------------------------

    initial begin

        $dumpfile("Simulation/Day17/matmul_2x2.vcd");
        $dumpvars(0, matmul_2x2_tb);

        reset = 1'b1;
        start = 1'b0;

        a00 = 0; a01 = 0; a10 = 0; a11 = 0;
        b00 = 0; b01 = 0; b10 = 0; b11 = 0;

        cycle = 0;
        pass_count = 0;
        fail_count = 0;

        repeat (3) @(posedge clk);

        @(negedge clk);

        reset = 1'b0;

        $display("--------------------------------");
        $display("DAY17 PARALLEL MATMUL TEST START");
        $display("--------------------------------");

        //--------------------------------------------------
        // Test 1 : same data as Day16
        // A=[1 2;3 4]  B=[5 6;7 8]  C=[19 22;43 50]
        //--------------------------------------------------

        do_matmul(
            8'sd1, 8'sd2, 8'sd3, 8'sd4,
            8'sd5, 8'sd6, 8'sd7, 8'sd8,
            4'd1
        );

        latency1 = latency;

        check_matrix(32'sd19, 32'sd22, 32'sd43, 32'sd50, 4'd1);

        //--------------------------------------------------
        // Test 2 : signed negative numbers
        // A=[-1 2;3 -4]  B=[2 -1;0 3]
        //
        // C[0][0] = -1*2 + 2*0 = -2
        // C[0][1] = -1*-1 + 2*3 = 7
        // C[1][0] =  3*2 + -4*0 = 6
        // C[1][1] =  3*-1 + -4*3 = -15
        //--------------------------------------------------

        do_matmul(
            -8'sd1, 8'sd2, 8'sd3, -8'sd4,
            8'sd2, -8'sd1, 8'sd0, 8'sd3,
            4'd2
        );

        latency2 = latency;

        check_matrix(-32'sd2, 32'sd7, 32'sd6, -32'sd15, 4'd2);

        //--------------------------------------------------
        // Summary
        //--------------------------------------------------

        $display("");
        $display("--------------------------------");
        $display("LATENCY COMPARISON");
        $display("  Day16 serial   : ~88 cycles (4 tasks x ~22)");
        $display("  Day17 parallel : %0d cycles (test1)", latency1);
        $display("  Day17 parallel : %0d cycles (test2)", latency2);

        $display("");
        if (fail_count == 0) begin

            $display("###############################");
            $display("#  DAY17 PARALLEL MATMUL PASS #");
            $display("###############################");

        end
        else begin

            $display("###############################");
            $display("#  DAY17 PARALLEL MATMUL FAIL #");
            $display("###############################");

        end

        $display("--------------------------------");

        #20;

        $finish;

    end

endmodule

Simulation/Day17/matmul_2x2.vcd
$date
	Sat Aug  8 11:11:44 2026
$end
$version
	Icarus Verilog
$end
$timescale
	1ps
$end
$scope module matmul_2x2_tb $end
$var wire 1 ! done $end
$var wire 32 " c11 [31:0] $end
$var wire 32 # c10 [31:0] $end
$var wire 32 $ c01 [31:0] $end
$var wire 32 % c00 [31:0] $end
$var parameter 32 & ACC_WIDTH $end
$var parameter 32 ' DATA_WIDTH $end
$var reg 8 ( a00 [7:0] $end
$var reg 8 ) a01 [7:0] $end
$var reg 8 * a10 [7:0] $end
$var reg 8 + a11 [7:0] $end
$var reg 8 , b00 [7:0] $end
$var reg 8 - b01 [7:0] $end
$var reg 8 . b10 [7:0] $end
$var reg 8 / b11 [7:0] $end
$var reg 1 0 clk $end
$var reg 32 1 cycle [31:0] $end
$var reg 32 2 done_cycle [31:0] $end
$var reg 32 3 latency [31:0] $end
$var reg 32 4 latency1 [31:0] $end
$var reg 32 5 latency2 [31:0] $end
$var reg 1 6 reset $end
$var reg 1 7 start $end
$var reg 32 8 start_cycle [31:0] $end
$var integer 32 9 fail_count [31:0] $end
$var integer 32 : pass_count [31:0] $end
$scope module dut $end
$var wire 8 ; a00 [7:0] $end
$var wire 8 < a01 [7:0] $end
$var wire 8 = a10 [7:0] $end
$var wire 8 > a11 [7:0] $end
$var wire 8 ? b00 [7:0] $end
$var wire 8 @ b01 [7:0] $end
$var wire 8 A b10 [7:0] $end
$var wire 8 B b11 [7:0] $end
$var wire 1 0 clk $end
$var wire 1 6 reset $end
$var wire 1 7 start $end
$var wire 16 C p1_c11 [15:0] $end
$var wire 16 D p1_c10 [15:0] $end
$var wire 16 E p1_c01 [15:0] $end
$var wire 16 F p1_c00 [15:0] $end
$var wire 16 G p0_c11 [15:0] $end
$var wire 16 H p0_c10 [15:0] $end
$var wire 16 I p0_c01 [15:0] $end
$var wire 16 J p0_c00 [15:0] $end
$var parameter 32 K ACC_WIDTH $end
$var parameter 32 L DATA_WIDTH $end
$var parameter 2 M S_IDLE $end
$var parameter 2 N S_MAC1 $end
$var parameter 2 O S_MAC2 $end
$var reg 32 P acc00 [31:0] $end
$var reg 32 Q acc01 [31:0] $end
$var reg 32 R acc10 [31:0] $end
$var reg 32 S acc11 [31:0] $end
$var reg 32 T c00 [31:0] $end
$var reg 32 U c01 [31:0] $end
$var reg 32 V c10 [31:0] $end
$var reg 32 W c11 [31:0] $end
$var reg 1 ! done $end
$var reg 2 X state [1:0] $end
$upscope $end
$scope task check_matrix $end
$upscope $end
$scope task do_matmul $end
$upscope $end
$upscope $end
$enddefinitions $end
$comment Show the parameter values. $end
$dumpall
b10 O
b1 N
b0 M
b1000 L
b100000 K
b1000 '
b100000 &
$end
#0
$dumpvars
bx X
bx W
bx V
bx U
bx T
bx S
bx R
bx Q
bx P
b0 J
b0 I
b0 H
b0 G
b0 F
b0 E
b0 D
b0 C
b0 B
b0 A
b0 @
b0 ?
b0 >
b0 =
b0 <
b0 ;
b0 :
b0 9
bx 8
07
16
bx 5
bx 4
bx 3
bx 2
b0 1
00
b0 /
b0 .
b0 -
b0 ,
b0 +
b0 *
b0 )
b0 (
bx %
bx $
bx #
bx "
x!
$end
#5000
0!
b0 "
b0 W
b0 #
b0 V
b0 $
b0 U
b0 %
b0 T
b0 S
b0 R
b0 Q
b0 P
b0 X
b1 1
10
#10000
00
#15000
b10 1
10
#20000
00
#25000
b11 1
10
#30000
06
00
#35000
b100 1
10
#40000
17
b10000 E
b100000 C
b1000 /
b1000 B
b1110 F
b11100 D
b111 .
b111 A
b110 I
b10010 G
b110 -
b110 @
b101 J
b1111 H
b101 ,
b101 ?
b100 +
b100 >
b11 *
b11 =
b10 )
b10 <
b1 (
b1 ;
00
#45000
b1 X
b101 1
10
#50000
07
00
#55000
b110 1
b10 X
b10010 S
b1111 R
b110 Q
b101 P
b101 8
10
#60000
00
#65000
b1 :
b10 4
b10 3
b111 2
b0 X
1!
b110010 "
b110010 W
b110010 S
b101011 #
b101011 V
b101011 R
b10110 $
b10110 U
b10110 Q
b10011 %
b10011 T
b10011 P
b111 1
10
#70000
17
b110 E
b11 /
b11 B
b0 F
b0 .
b0 A
b1111111111111101 G
b11111111 -
b11111111 @
b110 H
b10 ,
b10 ?
b0 D
b1111111111110100 C
b11111100 +
b11111100 >
b1111111111111110 J
b1 I
b11111111 (
b11111111 ;
00
#75000
b1000 1
b1 X
b0 S
b0 R
b0 Q
b0 P
0!
10
#80000
07
00
#85000
b10 X
b11111111111111111111111111111101 S
b110 R
b1 Q
b11111111111111111111111111111110 P
b1001 1
b1000 8
10
#90000
00
#95000
b10 :
b10 5
b1010 2
b1010 1
b0 X
1!
b11111111111111111111111111110001 "
b11111111111111111111111111110001 W
b11111111111111111111111111110001 S
b110 #
b110 V
b111 $
b111 U
b111 Q
b11111111111111111111111111111110 %
b11111111111111111111111111111110 T
10
#100000
00
#105000
0!
b1011 1
10
#110000
00
#115000
b1100 1
10
