RTL/Day07/mac_unit.v
module mac_unit #(
    parameter DATA_WIDTH = 8
)(
    input wire clk,
    input wire reset,

    input wire [DATA_WIDTH-1:0] A,
    input wire [DATA_WIDTH-1:0] B,

    output reg [2*DATA_WIDTH-1:0] ACC
);


always @(posedge clk)
begin

    if(reset)

        ACC <= 0;

    else

        ACC <= ACC + (A * B);

end


endmodule

Testbench/Day07/mac_tb.v
`timescale 1ns/1ps


module mac_tb;


parameter DATA_WIDTH = 8;


reg clk;
reg reset;


reg [DATA_WIDTH-1:0] A;
reg [DATA_WIDTH-1:0] B;


wire [2*DATA_WIDTH-1:0] ACC;



mac_unit #(
    .DATA_WIDTH(DATA_WIDTH)
)
dut(
    .clk(clk),
    .reset(reset),

    .A(A),
    .B(B),

    .ACC(ACC)
);



/*
    Clock generation

    period = 10ns
*/
always #5 clk = ~clk;



initial begin


    // waveform
    $dumpfile("../../Simulation/Day07/mac.vcd");
    $dumpvars(0,mac_tb);


    // monitor
    $monitor(
        "time=%0t A=%d B=%d ACC=%d",
        $time,
        A,
        B,
        ACC
    );


    // initial state

    clk = 0;
    reset = 1;

    A = 0;
    B = 0;


    #10;


    // release reset

    reset = 0;


    // Cycle 1
    // ACC = 3*4 = 12

    A = 8'd3;
    B = 8'd4;


    #10;


    // Cycle 2
    // ACC = 12 + 2*5 = 22

    A = 8'd2;
    B = 8'd5;


    #10;


    // Cycle 3
    // ACC = 22 + 1*10 = 32

    A = 8'd1;
    B = 8'd10;


    #10;


    $finish;


end


endmodule

Simulation/Day07/mac.vcd
$date
	Wed Jul 29 22:07:23 2026
$end
$version
	Icarus Verilog
$end
$timescale
	1ps
$end
$scope module mac_tb $end
$var wire 16 ! ACC [15:0] $end
$var parameter 32 " DATA_WIDTH $end
$var reg 8 # A [7:0] $end
$var reg 8 $ B [7:0] $end
$var reg 1 % clk $end
$var reg 1 & reset $end
$scope module dut $end
$var wire 8 ' A [7:0] $end
$var wire 8 ( B [7:0] $end
$var wire 1 % clk $end
$var wire 1 & reset $end
$var parameter 32 ) DATA_WIDTH $end
$var reg 16 * ACC [15:0] $end
$upscope $end
$upscope $end
$enddefinitions $end
$comment Show the parameter values. $end
$dumpall
b1000 )
b1000 "
$end
#0
$dumpvars
bx *
b0 (
b0 '
1&
0%
b0 $
b0 #
bx !
$end
#5000
b0 !
b0 *
1%
#10000
0%
b100 $
b100 (
b11 #
b11 '
0&
#15000
b1100 !
b1100 *
1%
#20000
0%
b101 $
b101 (
b10 #
b10 '
#25000
b10110 !
b10110 *
1%
#30000
0%
b1010 $
b1010 (
b1 #
b1 '
#35000
b100000 !
b100000 *
1%
