RTL/Day03/counter8.v
module counter8(
    input clk,
    input reset,
    output reg [7:0] count
);


always @(posedge clk)
begin

    if(reset)
        count <= 8'b00000000;

    else
        count <= count + 1;

end


endmodule

Testbench/Day03/counter8_tb.v
`timescale 1ns/1ps

module counter8_tb;


reg clk;
reg reset;

wire [7:0] count;


counter8 uut(
    .clk(clk),
    .reset(reset),
    .count(count)
);


// Clock

initial begin

    clk = 0;

    forever #5 clk = ~clk;

end



// Test

initial begin

    $dumpfile("counter8.vcd");
    $dumpvars(0,counter8_tb);


    // Reset
    reset = 1;


    #10;


    // Start counting
    reset = 0;


    #80;


    $finish;

end


endmodule

Simulation/Day03/counter8/counter8.vcd
$date
	Sat Jul 18 23:08:32 2026
$end
$version
	Icarus Verilog
$end
$timescale
	1ps
$end
$scope module counter8_tb $end
$var wire 8 ! count [7:0] $end
$var reg 1 " clk $end
$var reg 1 # reset $end
$scope module uut $end
$var wire 1 " clk $end
$var wire 1 # reset $end
$var reg 8 $ count [7:0] $end
$upscope $end
$upscope $end
$enddefinitions $end
$comment Show the parameter values. $end
$dumpall
$end
#0
$dumpvars
bx $
1#
0"
bx !
$end
#5000
b0 !
b0 $
1"
#10000
0"
0#
#15000
b1 !
b1 $
1"
#20000
0"
#25000
b10 !
b10 $
1"
#30000
0"
#35000
b11 !
b11 $
1"
#40000
0"
#45000
b100 !
b100 $
1"
#50000
0"
#55000
b101 !
b101 $
1"
#60000
0"
#65000
b110 !
b110 $
1"
#70000
0"
#75000
b111 !
b111 $
1"
#80000
0"
#85000
b1000 !
b1000 $
1"
