RTL/Day09/pipeline_mac.v
module pipeline_mac #(

    parameter DATA_WIDTH = 8,
    parameter ACC_WIDTH  = 32

)
(

    input clk,
    input rst,


    input [DATA_WIDTH-1:0] activation,
    input [DATA_WIDTH-1:0] weight,

    input [ACC_WIDTH-1:0] partial_sum,


    output [ACC_WIDTH-1:0] result

);



    // Stage 1 registers

    reg [(2*DATA_WIDTH)-1:0] product_reg;

    reg [ACC_WIDTH-1:0] partial_sum_reg;



    // Stage 2 register

    reg [ACC_WIDTH-1:0] result_reg;



    always @(posedge clk)

    begin

        if(rst)

        begin

            product_reg <= 0;

            partial_sum_reg <= 0;

            result_reg <= 0;

        end


        else

        begin


            // Stage 1

            product_reg <= activation * weight;

            partial_sum_reg <= partial_sum;



            // Stage 2

            result_reg <= product_reg + partial_sum_reg;


        end


    end



    assign result = result_reg;



endmodule

Testbench/Day09/pipeline_mac_tb.v
`timescale 1ns/1ps


module pipeline_mac_tb;


parameter DATA_WIDTH = 8;
parameter ACC_WIDTH  = 32;



// Clock

reg clk;
reg rst;



// Input

reg [DATA_WIDTH-1:0] activation;
reg [DATA_WIDTH-1:0] weight;

reg [ACC_WIDTH-1:0] partial_sum;



// Output

wire [ACC_WIDTH-1:0] result;



// Expected pipeline

reg [ACC_WIDTH-1:0] expected_stage1;
reg [ACC_WIDTH-1:0] expected_stage2;



integer pass_count;
integer fail_count;



// DUT

pipeline_mac #(

    .DATA_WIDTH(DATA_WIDTH),
    .ACC_WIDTH(ACC_WIDTH)

)

dut
(

    .clk(clk),
    .rst(rst),

    .activation(activation),
    .weight(weight),

    .partial_sum(partial_sum),

    .result(result)

);



// Clock 10ns period

always #5 clk = ~clk;



// VCD

initial
begin

    $dumpfile("Simulation/Day09/pipeline_mac.vcd");

    $dumpvars(0,pipeline_mac_tb);

end





// Automatic checker

task check_output;

input [ACC_WIDTH-1:0] expected;


begin


    if(result == expected)

    begin

        $display(
        "PASS time=%0t result=%d expected=%d",
        $time,
        result,
        expected
        );


        pass_count = pass_count + 1;


    end

    else

    begin

        $display(
        "FAIL time=%0t result=%d expected=%d",
        $time,
        result,
        expected
        );


        fail_count = fail_count + 1;

    end


end

endtask





// Expected model pipeline

always @(posedge clk)

begin

    if(!rst)

    begin

        // Stage2 output check

        #1;

        check_output(expected_stage2);


        // shift expected values

        expected_stage2 <= expected_stage1;


    end


end





// Main stimulus

initial
begin


    clk = 0;

    rst = 1;



    activation = 0;

    weight = 0;

    partial_sum = 0;



    expected_stage1 = 0;

    expected_stage2 = 0;


    pass_count = 0;

    fail_count = 0;



    // Reset

    repeat(2)

        @(posedge clk);



    rst = 0;



    /*
        Input stream


        MAC1:
        2*3+10=16


        MAC2:
        4*5+20=40


        MAC3:
        10*2+30=50

    */



    @(negedge clk);

    activation = 8'd2;

    weight = 8'd3;

    partial_sum = 32'd10;

    expected_stage1 = 32'd16;




    @(negedge clk);

    activation = 8'd4;

    weight = 8'd5;

    partial_sum = 32'd20;

    expected_stage1 = 32'd40;




    @(negedge clk);

    activation = 8'd10;

    weight = 8'd2;

    partial_sum = 32'd30;

    expected_stage1 = 32'd50;




    // stop input

    @(negedge clk);

    activation = 0;

    weight = 0;

    partial_sum = 0;

    expected_stage1 = 0;




    // wait pipeline drain

    repeat(3)

        @(posedge clk);



    #5;


    $display("----------------------");

    $display(
    "PASS=%d FAIL=%d",
    pass_count,
    fail_count
    );

    $display("----------------------");


    $finish;


end





// Monitor

initial
begin


    $monitor(

    "time=%0t | act=%d weight=%d ps=%d | product=%d ps_reg=%d result=%d",

    $time,

    activation,

    weight,

    partial_sum,

    dut.product_reg,

    dut.partial_sum_reg,

    result

    );


end



endmodule

Simulation/Day09/pipeline_mac.vcd
$date
	Fri Jul 31 11:01:19 2026
$end
$version
	Icarus Verilog
$end
$timescale
	1ps
$end
$scope module pipeline_mac_tb $end
$var wire 32 ! result [31:0] $end
$var parameter 32 " ACC_WIDTH $end
$var parameter 32 # DATA_WIDTH $end
$var reg 8 $ activation [7:0] $end
$var reg 1 % clk $end
$var reg 32 & expected_stage1 [31:0] $end
$var reg 32 ' expected_stage2 [31:0] $end
$var reg 32 ( partial_sum [31:0] $end
$var reg 1 ) rst $end
$var reg 8 * weight [7:0] $end
$var integer 32 + fail_count [31:0] $end
$var integer 32 , pass_count [31:0] $end
$scope module dut $end
$var wire 8 - activation [7:0] $end
$var wire 1 % clk $end
$var wire 32 . partial_sum [31:0] $end
$var wire 32 / result [31:0] $end
$var wire 1 ) rst $end
$var wire 8 0 weight [7:0] $end
$var parameter 32 1 ACC_WIDTH $end
$var parameter 32 2 DATA_WIDTH $end
$var reg 32 3 partial_sum_reg [31:0] $end
$var reg 16 4 product_reg [15:0] $end
$var reg 32 5 result_reg [31:0] $end
$upscope $end
$scope task check_output $end
$var reg 32 6 expected [31:0] $end
$upscope $end
$upscope $end
$enddefinitions $end
$comment Show the parameter values. $end
$dumpall
b1000 2
b100000 1
b1000 #
b100000 "
$end
#0
$dumpvars
bx 6
bx 5
bx 4
bx 3
b0 0
bx /
b0 .
b0 -
b0 ,
b0 +
b0 *
1)
b0 (
b0 '
b0 &
0%
b0 $
bx !
$end
#5000
b0 !
b0 /
b0 5
b0 3
b0 4
1%
#10000
0%
#15000
0)
1%
#20000
b10000 &
b1010 (
b1010 .
b11 *
b11 0
b10 $
b10 -
0%
#25000
b1010 3
b110 4
1%
#26000
b10000 '
b1 ,
b0 6
#30000
b101000 &
b10100 (
b10100 .
b101 *
b101 0
b100 $
b100 -
0%
#35000
b10000 !
b10000 /
b10000 5
b10100 3
b10100 4
1%
#36000
b101000 '
b10 ,
b10000 6
#40000
b110010 &
b11110 (
b11110 .
b10 *
b10 0
b1010 $
b1010 -
0%
#45000
b101000 !
b101000 /
b101000 5
b11110 3
1%
#46000
b110010 '
b11 ,
b101000 6
#50000
b0 &
b0 (
b0 .
b0 *
b0 0
b0 $
b0 -
0%
#55000
b110010 !
b110010 /
b110010 5
b0 3
b0 4
1%
#56000
b0 '
b100 ,
b110010 6
#60000
0%
#65000
b0 !
b0 /
b0 5
1%
#66000
b101 ,
b0 6
#70000
0%
#75000
1%
#76000
b110 ,
