RTL/Day14/Compute/pe_unit.v
module pe_unit #(

    parameter DATA_WIDTH = 8,
    parameter ACC_WIDTH  = 32

)(

    input wire clk,
    input wire reset,

    input wire compute_enable,
    input wire clear_acc,

    input wire signed [DATA_WIDTH-1:0]
    activation_in,

    input wire signed [DATA_WIDTH-1:0]
    weight_in,

    output reg signed [DATA_WIDTH-1:0]
    activation_out,

    output reg signed [DATA_WIDTH-1:0]
    weight_out,

    output wire signed [ACC_WIDTH-1:0]
    psum_out

);

    //--------------------------------------------------
    // Internal accumulator
    //--------------------------------------------------

    reg signed [ACC_WIDTH-1:0]
    accumulator;

    wire signed [(2*DATA_WIDTH)-1:0]
    product;

    assign product = activation_in * weight_in;

    /*
     * Directly expose the accumulator.
     *
     * The previous registered psum_out lagged one clock
     * behind accumulator and made result observation harder.
     */
    assign psum_out = accumulator;

    //--------------------------------------------------
    // PE sequential behavior
    //--------------------------------------------------

    always @(posedge clk) begin

        if (reset) begin

            activation_out <= {DATA_WIDTH{1'b0}};
            weight_out     <= {DATA_WIDTH{1'b0}};
            accumulator    <= {ACC_WIDTH{1'b0}};

        end
        else begin

            if (clear_acc)
                accumulator <= {ACC_WIDTH{1'b0}};

            else if (compute_enable)
                accumulator <= accumulator + product;

            if (compute_enable) begin
                activation_out <= activation_in;
                weight_out     <= weight_in;
            end

        end

    end

endmodule

RTL/Day18/systolic_matmul_2x2.v
`timescale 1ns/1ps

//==========================================================
// Day 18 : Systolic 2x2 Matrix Multiply
//==========================================================
//
// Four pe_unit (reused from Day14) arranged as a 2x2
// systolic array.
//
// Dataflow:
//   activations flow  left  -> right  (one row of A per row)
//   weights     flow  top   -> down   (one column of B per col)
//   each PE accumulates  activation_in * weight_in  in place
//
// Skew schedule (the key insight of Day18):
//   A[i][k] enters row i at cycle  k + i
//   B[k][j] enters col j at cycle  k + j
//
//   Because activation needs j hops to reach PE(i,j) and
//   weight needs i hops, both arrive with index
//   k = t - 1 - i - j  -> they match, so PE(i,j) computes
//   C[i][j] = sum_k A[i][k] * B[k][j].
//
// Latency: 5 cycles
//   S_CLR clear + S_FEED0/1/2 (pipeline fill + compute)
//   + S_DRAIN (last PE finishes)
//==========================================================

module systolic_matmul_2x2 #(

    parameter DATA_WIDTH = 8,
    parameter ACC_WIDTH  = 32

)(

    input wire clk,
    input wire reset,
    input wire start,

    //--------------------------------------------------
    // A matrix (row-major), 2x2
    //--------------------------------------------------

    input  wire signed [DATA_WIDTH-1:0] a00, a01,
    input  wire signed [DATA_WIDTH-1:0] a10, a11,

    //--------------------------------------------------
    // B matrix (row-major), 2x2
    //--------------------------------------------------

    input  wire signed [DATA_WIDTH-1:0] b00, b01,
    input  wire signed [DATA_WIDTH-1:0] b10, b11,

    //--------------------------------------------------
    // C matrix = A x B, 2x2 (combinational from accumulators)
    //--------------------------------------------------

    output wire signed [ACC_WIDTH-1:0] c00, c01,
    output wire signed [ACC_WIDTH-1:0] c10, c11,

    output reg done

);

    //--------------------------------------------------
    // Controller state encoding
    //--------------------------------------------------

    localparam S_IDLE  = 3'd0;  // wait for start
    localparam S_CLR   = 3'd1;  // clear all PE accumulators
    localparam S_FEED0 = 3'd2;  // feed k=0 terms  (skew)
    localparam S_FEED1 = 3'd3;  // feed k=1 terms
    localparam S_FEED2 = 3'd4;  // feed the last skewed elements
    localparam S_DRAIN = 3'd5;  // drain the array, assert done

    reg [2:0] state;

    //--------------------------------------------------
    // Boundary feed signals (combinational, per state)
    //--------------------------------------------------

    reg signed [DATA_WIDTH-1:0] act_b0;   // row 0 left boundary
    reg signed [DATA_WIDTH-1:0] act_b1;   // row 1 left boundary
    reg signed [DATA_WIDTH-1:0] w_b0;     // col 0 top boundary
    reg signed [DATA_WIDTH-1:0] w_b1;     // col 1 top boundary

    //--------------------------------------------------
    // PE-to-PE forwarding wires
    //--------------------------------------------------

    wire signed [DATA_WIDTH-1:0] a_00_to_01;  // PE00 -> PE01 activation
    wire signed [DATA_WIDTH-1:0] a_10_to_11;  // PE10 -> PE11 activation
    wire signed [DATA_WIDTH-1:0] w_00_to_10;  // PE00 -> PE10 weight
    wire signed [DATA_WIDTH-1:0] w_01_to_11;  // PE01 -> PE11 weight

    // unused array exit wires (kept for completeness)
    wire signed [DATA_WIDTH-1:0] a_exit0, a_exit1;
    wire signed [DATA_WIDTH-1:0] w_exit0, w_exit1;

    //--------------------------------------------------
    // Control signals for the PEs
    //--------------------------------------------------

    wire compute_en = (state != S_IDLE) && (state != S_CLR);
    wire clear_acc  = (state == S_CLR);

    //--------------------------------------------------
    // Skew-scheduled boundary values
    //
    // S_FEED0: A[0][0], B[0][0]              (k=0, no skew)
    // S_FEED1: A[0][1], A[1][0], B[1][0], B[0][1]
    // S_FEED2: A[1][1], B[1][1]              (last skewed elements)
    //--------------------------------------------------

    always @(*) begin

        act_b0 = {DATA_WIDTH{1'b0}};
        act_b1 = {DATA_WIDTH{1'b0}};
        w_b0   = {DATA_WIDTH{1'b0}};
        w_b1   = {DATA_WIDTH{1'b0}};

        case (state)

            S_FEED0: begin
                act_b0 = a00;
                w_b0   = b00;
            end

            S_FEED1: begin
                act_b0 = a01;
                act_b1 = a10;
                w_b0   = b10;
                w_b1   = b01;
            end

            S_FEED2: begin
                act_b1 = a11;
                w_b1   = b11;
            end

            default: ;
        endcase

    end

    //--------------------------------------------------
    // 2x2 PE array (reusing the Day14 pe_unit IP)
    //--------------------------------------------------

    pe_unit #(
        .DATA_WIDTH(DATA_WIDTH),
        .ACC_WIDTH(ACC_WIDTH)
    ) pe_00 (
        .clk(clk),
        .reset(reset),
        .compute_enable(compute_en),
        .clear_acc(clear_acc),
        .activation_in(act_b0),
        .weight_in(w_b0),
        .activation_out(a_00_to_01),
        .weight_out(w_00_to_10),
        .psum_out(c00)
    );

    pe_unit #(
        .DATA_WIDTH(DATA_WIDTH),
        .ACC_WIDTH(ACC_WIDTH)
    ) pe_01 (
        .clk(clk),
        .reset(reset),
        .compute_enable(compute_en),
        .clear_acc(clear_acc),
        .activation_in(a_00_to_01),
        .weight_in(w_b1),
        .activation_out(a_exit0),
        .weight_out(w_01_to_11),
        .psum_out(c01)
    );

    pe_unit #(
        .DATA_WIDTH(DATA_WIDTH),
        .ACC_WIDTH(ACC_WIDTH)
    ) pe_10 (
        .clk(clk),
        .reset(reset),
        .compute_enable(compute_en),
        .clear_acc(clear_acc),
        .activation_in(act_b1),
        .weight_in(w_00_to_10),
        .activation_out(a_10_to_11),
        .weight_out(w_exit0),
        .psum_out(c10)
    );

    pe_unit #(
        .DATA_WIDTH(DATA_WIDTH),
        .ACC_WIDTH(ACC_WIDTH)
    ) pe_11 (
        .clk(clk),
        .reset(reset),
        .compute_enable(compute_en),
        .clear_acc(clear_acc),
        .activation_in(a_10_to_11),
        .weight_in(w_01_to_11),
        .activation_out(a_exit1),
        .weight_out(w_exit1),
        .psum_out(c11)
    );

    //--------------------------------------------------
    // Controller
    //--------------------------------------------------

    always @(posedge clk) begin

        if (reset) begin

            state <= S_IDLE;
            done  <= 1'b0;

        end
        else begin

            done <= 1'b0;

            case (state)

                S_IDLE: begin
                    if (start)
                        state <= S_CLR;
                end

                S_CLR: begin
                    state <= S_FEED0;
                end

                S_FEED0: begin
                    state <= S_FEED1;
                end

                S_FEED1: begin
                    state <= S_FEED2;
                end

                S_FEED2: begin
                    state <= S_DRAIN;
                end

                S_DRAIN: begin
                    done <= 1'b1;
                    state <= S_IDLE;
                end

                default: begin
                    state <= S_IDLE;
                end

            endcase

        end

    end

endmodule

Testbench/Day18/systolic_matmul_2x2_tb.v
`timescale 1ns/1ps

//==========================================================
// Day 18 : Systolic 2x2 Matrix Multiply - Testbench
//==========================================================
//
// Test 1: A=[1 2;3 4]  B=[5 6;7 8]   -> C=[19 22;43 50]
// Test 2: A=[-1 2;3 -4] B=[2 -1;0 3] -> C=[-2 7;6 -15]
//
// Compares latency with Day16 (serial ~88) and
// Day17 (parallel 2 cycles).
//==========================================================

module systolic_matmul_2x2_tb;

    localparam DATA_WIDTH = 8;
    localparam ACC_WIDTH  = 32;

    //--------------------------------------------------
    // Clock and reset
    //--------------------------------------------------

    reg clk;
    reg reset;
    reg start;

    //--------------------------------------------------
    // Matrix inputs
    //--------------------------------------------------

    reg signed [DATA_WIDTH-1:0] a00, a01, a10, a11;
    reg signed [DATA_WIDTH-1:0] b00, b01, b10, b11;

    //--------------------------------------------------
    // Result outputs
    //--------------------------------------------------

    wire signed [ACC_WIDTH-1:0] c00, c01, c10, c11;
    wire done;

    //--------------------------------------------------
    // Latency measurement
    //--------------------------------------------------

    reg [31:0] cycle;
    reg [31:0] start_cycle;
    reg [31:0] done_cycle;
    reg [31:0] latency;
    reg [31:0] latency1;
    reg [31:0] latency2;

    //--------------------------------------------------
    // Pass/fail counters
    //--------------------------------------------------

    integer pass_count;
    integer fail_count;

    //--------------------------------------------------
    // DUT : systolic array (uses pe_unit from Day14)
    //--------------------------------------------------

    systolic_matmul_2x2 #(

        .DATA_WIDTH(DATA_WIDTH),
        .ACC_WIDTH(ACC_WIDTH)

    ) dut (

        .clk(clk),
        .reset(reset),
        .start(start),

        .a00(a00), .a01(a01), .a10(a10), .a11(a11),

        .b00(b00), .b01(b01), .b10(b10), .b11(b11),

        .c00(c00), .c01(c01), .c10(c10), .c11(c11),

        .done(done)

    );

    //--------------------------------------------------
    // Clock generation : 10 ns period
    //--------------------------------------------------

    initial begin

        clk = 1'b0;

        forever #5 clk = ~clk;

    end

    //--------------------------------------------------
    // Cycle counter
    //--------------------------------------------------

    always @(posedge clk) cycle <= cycle + 1'b1;

    //--------------------------------------------------
    // Drive one matrix multiply and measure latency
    //--------------------------------------------------

    task automatic do_matmul (

        input signed [DATA_WIDTH-1:0] pa00, pa01, pa10, pa11,
        input signed [DATA_WIDTH-1:0] pb00, pb01, pb10, pb11,

        input [3:0] test_id

    );

        begin

            @(negedge clk);

            a00 = pa00; a01 = pa01; a10 = pa10; a11 = pa11;
            b00 = pb00; b01 = pb01; b10 = pb10; b11 = pb11;

            start = 1'b1;

            @(negedge clk);

            start = 1'b0;

            @(posedge clk);       // DUT samples start here
            start_cycle = cycle;

            @(posedge done);      // completion pulse
            done_cycle  = cycle;

            latency = done_cycle - start_cycle;

            $display("");
            $display("Test %0d:", test_id);
            $display("  A = [%0d %0d]     B = [%0d %0d]",
                a00, a01, b00, b01);
            $display("      [%0d %0d]         [%0d %0d]",
                a10, a11, b10, b11);
            $display("  C = [%0d %0d]", c00, c01);
            $display("      [%0d %0d]", c10, c11);
            $display("  latency = %0d cycles", latency);

        end

    endtask

    //--------------------------------------------------
    // Check helper
    //--------------------------------------------------

    task automatic check_matrix (

        input signed [ACC_WIDTH-1:0] e00, e01, e10, e11,
        input [3:0] test_id

    );

        begin

            if (
                c00 === e00 &&
                c01 === e01 &&
                c10 === e10 &&
                c11 === e11
            ) begin

                $display("  TEST%0d PASS : C = [%0d %0d; %0d %0d]",
                    test_id, e00, e01, e10, e11);

                pass_count = pass_count + 1;

            end
            else begin

                $display("  TEST%0d FAIL : got [%0d %0d; %0d %0d], expected [%0d %0d; %0d %0d]",
                    test_id, c00, c01, c10, c11, e00, e01, e10, e11);

                fail_count = fail_count + 1;

            end

        end

    endtask
    //--------------------------------------------------
    // Main test sequence
    //--------------------------------------------------

    initial begin

        $dumpfile("Simulation/Day18/systolic_matmul_2x2.vcd");
        $dumpvars(0, systolic_matmul_2x2_tb);

        reset = 1'b1;
        start = 1'b0;

        a00 = 0; a01 = 0; a10 = 0; a11 = 0;
        b00 = 0; b01 = 0; b10 = 0; b11 = 0;

        cycle = 0;
        pass_count = 0;
        fail_count = 0;

        repeat (3) @(posedge clk);

        @(negedge clk);

        reset = 1'b0;

        $display("--------------------------------");
        $display("DAY18 SYSTOLIC MATMUL TEST START");
        $display("--------------------------------");

        //--------------------------------------------------
        // Test 1 : same data as Day16/17
        // A=[1 2;3 4]  B=[5 6;7 8]  C=[19 22;43 50]
        //--------------------------------------------------

        do_matmul(
            8'sd1, 8'sd2, 8'sd3, 8'sd4,
            8'sd5, 8'sd6, 8'sd7, 8'sd8,
            4'd1
        );

        latency1 = latency;

        check_matrix(32'sd19, 32'sd22, 32'sd43, 32'sd50, 4'd1);

        //--------------------------------------------------
        // Test 2 : signed negative numbers
        // A=[-1 2;3 -4]  B=[2 -1;0 3]
        // C=[-2 7; 6 -15]
        //--------------------------------------------------

        do_matmul(
            -8'sd1, 8'sd2, 8'sd3, -8'sd4,
            8'sd2, -8'sd1, 8'sd0, 8'sd3,
            4'd2
        );

        latency2 = latency;

        check_matrix(-32'sd2, 32'sd7, 32'sd6, -32'sd15, 4'd2);

        //--------------------------------------------------
        // Summary
        //--------------------------------------------------

        $display("");
        $display("--------------------------------");
        $display("LATENCY COMPARISON (2x2 matrix)");
        $display("  Day16 serial    : ~88 cycles");
        $display("  Day17 parallel  :  2 cycles");
        $display("  Day18 systolic  : %0d cycles (test1)", latency1);
        $display("  Day18 systolic  : %0d cycles (test2)", latency2);
        $display("");
        $display("  Note: systolic is slightly slower for a tiny");
        $display("  2x2 case due to pipeline fill + drain, but it");
        $display("  wins at scale through data reuse (lower I/O).");

        $display("");
        if (fail_count == 0) begin

            $display("###############################");
            $display("#  DAY18 SYSTOLIC MATMUL PASS #");
            $display("###############################");

        end
        else begin

            $display("###############################");
            $display("#  DAY18 SYSTOLIC MATMUL FAIL #");
            $display("###############################");

        end

        $display("--------------------------------");

        #20;

        $finish;

    end

endmodule

Simulation/Day18/systolic_matmul_2x2.vcd
$date
	Sat Aug  8 11:25:24 2026
$end
$version
	Icarus Verilog
$end
$timescale
	1ps
$end
$scope module systolic_matmul_2x2_tb $end
$var wire 1 ! done $end
$var wire 32 " c11 [31:0] $end
$var wire 32 # c10 [31:0] $end
$var wire 32 $ c01 [31:0] $end
$var wire 32 % c00 [31:0] $end
$var parameter 32 & ACC_WIDTH $end
$var parameter 32 ' DATA_WIDTH $end
$var reg 8 ( a00 [7:0] $end
$var reg 8 ) a01 [7:0] $end
$var reg 8 * a10 [7:0] $end
$var reg 8 + a11 [7:0] $end
$var reg 8 , b00 [7:0] $end
$var reg 8 - b01 [7:0] $end
$var reg 8 . b10 [7:0] $end
$var reg 8 / b11 [7:0] $end
$var reg 1 0 clk $end
$var reg 32 1 cycle [31:0] $end
$var reg 32 2 done_cycle [31:0] $end
$var reg 32 3 latency [31:0] $end
$var reg 32 4 latency1 [31:0] $end
$var reg 32 5 latency2 [31:0] $end
$var reg 1 6 reset $end
$var reg 1 7 start $end
$var reg 32 8 start_cycle [31:0] $end
$var integer 32 9 fail_count [31:0] $end
$var integer 32 : pass_count [31:0] $end
$scope module dut $end
$var wire 8 ; a00 [7:0] $end
$var wire 8 < a01 [7:0] $end
$var wire 8 = a10 [7:0] $end
$var wire 8 > a11 [7:0] $end
$var wire 8 ? b00 [7:0] $end
$var wire 8 @ b01 [7:0] $end
$var wire 8 A b10 [7:0] $end
$var wire 8 B b11 [7:0] $end
$var wire 1 0 clk $end
$var wire 1 C compute_en $end
$var wire 1 6 reset $end
$var wire 1 7 start $end
$var wire 8 D w_exit1 [7:0] $end
$var wire 8 E w_exit0 [7:0] $end
$var wire 8 F w_01_to_11 [7:0] $end
$var wire 8 G w_00_to_10 [7:0] $end
$var wire 1 H clear_acc $end
$var wire 32 I c11 [31:0] $end
$var wire 32 J c10 [31:0] $end
$var wire 32 K c01 [31:0] $end
$var wire 32 L c00 [31:0] $end
$var wire 8 M a_exit1 [7:0] $end
$var wire 8 N a_exit0 [7:0] $end
$var wire 8 O a_10_to_11 [7:0] $end
$var wire 8 P a_00_to_01 [7:0] $end
$var parameter 32 Q ACC_WIDTH $end
$var parameter 32 R DATA_WIDTH $end
$var parameter 3 S S_CLR $end
$var parameter 3 T S_DRAIN $end
$var parameter 3 U S_FEED0 $end
$var parameter 3 V S_FEED1 $end
$var parameter 3 W S_FEED2 $end
$var parameter 3 X S_IDLE $end
$var reg 8 Y act_b0 [7:0] $end
$var reg 8 Z act_b1 [7:0] $end
$var reg 1 ! done $end
$var reg 3 [ state [2:0] $end
$var reg 8 \ w_b0 [7:0] $end
$var reg 8 ] w_b1 [7:0] $end
$scope module pe_00 $end
$var wire 8 ^ activation_in [7:0] $end
$var wire 1 H clear_acc $end
$var wire 1 0 clk $end
$var wire 1 C compute_enable $end
$var wire 32 _ psum_out [31:0] $end
$var wire 1 6 reset $end
$var wire 8 ` weight_in [7:0] $end
$var wire 16 a product [15:0] $end
$var parameter 32 b ACC_WIDTH $end
$var parameter 32 c DATA_WIDTH $end
$var reg 32 d accumulator [31:0] $end
$var reg 8 e activation_out [7:0] $end
$var reg 8 f weight_out [7:0] $end
$upscope $end
$scope module pe_01 $end
$var wire 8 g activation_in [7:0] $end
$var wire 1 H clear_acc $end
$var wire 1 0 clk $end
$var wire 1 C compute_enable $end
$var wire 32 h psum_out [31:0] $end
$var wire 1 6 reset $end
$var wire 8 i weight_in [7:0] $end
$var wire 16 j product [15:0] $end
$var parameter 32 k ACC_WIDTH $end
$var parameter 32 l DATA_WIDTH $end
$var reg 32 m accumulator [31:0] $end
$var reg 8 n activation_out [7:0] $end
$var reg 8 o weight_out [7:0] $end
$upscope $end
$scope module pe_10 $end
$var wire 8 p activation_in [7:0] $end
$var wire 1 H clear_acc $end
$var wire 1 0 clk $end
$var wire 1 C compute_enable $end
$var wire 32 q psum_out [31:0] $end
$var wire 1 6 reset $end
$var wire 8 r weight_in [7:0] $end
$var wire 16 s product [15:0] $end
$var parameter 32 t ACC_WIDTH $end
$var parameter 32 u DATA_WIDTH $end
$var reg 32 v accumulator [31:0] $end
$var reg 8 w activation_out [7:0] $end
$var reg 8 x weight_out [7:0] $end
$upscope $end
$scope module pe_11 $end
$var wire 8 y activation_in [7:0] $end
$var wire 1 H clear_acc $end
$var wire 1 0 clk $end
$var wire 1 C compute_enable $end
$var wire 32 z psum_out [31:0] $end
$var wire 1 6 reset $end
$var wire 8 { weight_in [7:0] $end
$var wire 16 | product [15:0] $end
$var parameter 32 } ACC_WIDTH $end
$var parameter 32 ~ DATA_WIDTH $end
$var reg 32 !" accumulator [31:0] $end
$var reg 8 "" activation_out [7:0] $end
$var reg 8 #" weight_out [7:0] $end
$upscope $end
$upscope $end
$scope task check_matrix $end
$upscope $end
$scope task do_matmul $end
$upscope $end
$upscope $end
$enddefinitions $end
$comment Show the parameter values. $end
$dumpall
b1000 ~
b100000 }
b1000 u
b100000 t
b1000 l
b100000 k
b1000 c
b100000 b
b0 X
b100 W
b11 V
b10 U
b101 T
b1 S
b1000 R
b100000 Q
b1000 '
b100000 &
$end
#0
$dumpvars
bx #"
bx ""
bx !"
bx |
bx {
bx z
bx y
bx x
bx w
bx v
bx s
bx r
bx q
b0 p
bx o
bx n
bx m
bx j
b0 i
bx h
bx g
bx f
bx e
bx d
b0 a
b0 `
bx _
b0 ^
b0 ]
b0 \
bx [
b0 Z
b0 Y
bx P
bx O
bx N
bx M
bx L
bx K
bx J
bx I
xH
bx G
bx F
bx E
bx D
xC
b0 B
b0 A
b0 @
b0 ?
b0 >
b0 =
b0 <
b0 ;
b0 :
b0 9
bx 8
07
16
bx 5
bx 4
bx 3
bx 2
b0 1
00
b0 /
b0 .
b0 -
b0 ,
b0 +
b0 *
b0 )
b0 (
bx %
bx $
bx #
bx "
x!
$end
#5000
0C
b0 %
b0 L
b0 _
b0 d
b0 s
b0 G
b0 f
b0 r
b0 j
b0 P
b0 e
b0 g
b0 $
b0 K
b0 h
b0 m
b0 |
b0 F
b0 o
b0 {
b0 N
b0 n
b0 #
b0 J
b0 q
b0 v
b0 E
b0 x
b0 O
b0 w
b0 y
b0 "
b0 I
b0 z
b0 !"
b0 D
b0 #"
b0 M
b0 ""
0!
0H
b0 [
b1 1
10
#10000
00
#15000
b10 1
10
#20000
00
#25000
b11 1
10
#30000
06
00
#35000
b100 1
10
#40000
17
b1000 /
b1000 B
b111 .
b111 A
b110 -
b110 @
b101 ,
b101 ?
b100 +
b100 >
b11 *
b11 =
b10 )
b10 <
b1 (
b1 ;
00
#45000
1H
b1 [
b101 1
10
#50000
07
00
#55000
b101 a
b101 \
b101 `
b1 Y
b1 ^
1C
b110 1
0H
b10 [
b101 8
10
#60000
00
#65000
b110 j
b110 ]
b110 i
b1111 s
b11 Z
b11 p
b111 \
b111 `
b1110 a
b10 Y
b10 ^
b101 G
b101 f
b101 r
b1 P
b1 e
b1 g
b101 %
b101 L
b101 _
b101 d
b11 [
b111 1
10
#70000
00
#75000
b1000 ]
b1000 i
b0 \
b0 `
b100 Z
b100 p
b0 a
b0 Y
b0 ^
b1000 1
b100 [
b101 E
b101 x
b10010 |
b11 O
b11 w
b11 y
b1111 #
b1111 J
b1111 q
b1111 v
b110 F
b110 o
b110 {
b1 N
b1 n
b110 $
b110 K
b110 h
b110 m
b11100 s
b111 G
b111 f
b111 r
b10000 j
b10 P
b10 e
b10 g
b10011 %
b10011 L
b10011 _
b10011 d
10
#80000
00
#85000
b0 ]
b0 i
b0 Z
b0 p
b0 s
b0 G
b0 f
b0 r
b0 j
b0 P
b0 e
b0 g
b1000 F
b1000 o
b1000 {
b10 N
b10 n
b10110 $
b10110 K
b10110 h
b10110 m
b111 E
b111 x
b100000 |
b100 O
b100 w
b100 y
b101011 #
b101011 J
b101011 q
b101011 v
b110 D
b110 #"
b11 M
b11 ""
b10010 "
b10010 I
b10010 z
b10010 !"
b101 [
b1001 1
10
#90000
00
#95000
0C
b1 :
b101 4
b101 3
b1010 2
b1010 1
b0 [
1!
b1000 D
b1000 #"
b100 M
b100 ""
b110010 "
b110010 I
b110010 z
b110010 !"
b0 E
b0 x
b0 O
b0 w
b0 y
b0 |
b0 F
b0 o
b0 {
b0 N
b0 n
10
#100000
17
b11 /
b11 B
b0 .
b0 A
b11111111 -
b11111111 @
b10 ,
b10 ?
b11111100 +
b11111100 >
b11111111 (
b11111111 ;
00
#105000
1H
b1 [
0!
b1011 1
10
#110000
07
00
#115000
b1111111111111110 a
b10 \
b10 `
b11111111 Y
b11111111 ^
1C
b1100 1
0H
b10 [
b0 "
b0 I
b0 z
b0 !"
b0 #
b0 J
b0 q
b0 v
b0 $
b0 K
b0 h
b0 m
b0 %
b0 L
b0 _
b0 d
b1011 8
10
#120000
00
#125000
b1 j
b11111111 ]
b11111111 i
b110 s
b11 Z
b11 p
b0 \
b0 `
b0 a
b10 Y
b10 ^
b10 G
b10 f
b10 r
b11111111 P
b11111111 e
b11111111 g
b11111111111111111111111111111110 %
b11111111111111111111111111111110 L
b11111111111111111111111111111110 _
b11111111111111111111111111111110 d
b0 D
b0 #"
b0 M
b0 ""
b11 [
b1101 1
10
#130000
00
#135000
b11 ]
b11 i
b11111100 Z
b11111100 p
b0 Y
b0 ^
b1110 1
b100 [
b10 E
b10 x
b1111111111111101 |
b11 O
b11 w
b11 y
b110 #
b110 J
b110 q
b110 v
b11111111 F
b11111111 o
b11111111 {
b11111111 N
b11111111 n
b1 $
b1 K
b1 h
b1 m
b0 s
b0 G
b0 f
b0 r
b110 j
b10 P
b10 e
b10 g
10
#140000
00
#145000
b0 ]
b0 i
b0 Z
b0 p
b0 j
b0 P
b0 e
b0 g
b11 F
b11 o
b11 {
b10 N
b10 n
b111 $
b111 K
b111 h
b111 m
b0 E
b0 x
b1111111111110100 |
b11111100 O
b11111100 w
b11111100 y
b11111111 D
b11111111 #"
b11 M
b11 ""
b11111111111111111111111111111101 "
b11111111111111111111111111111101 I
b11111111111111111111111111111101 z
b11111111111111111111111111111101 !"
b101 [
b1111 1
10
#150000
00
#155000
0C
b10 :
b101 5
b10000 2
b10000 1
b0 [
1!
b11 D
b11 #"
b11111100 M
b11111100 ""
b11111111111111111111111111110001 "
b11111111111111111111111111110001 I
b11111111111111111111111111110001 z
b11111111111111111111111111110001 !"
b0 O
b0 w
b0 y
b0 |
b0 F
b0 o
b0 {
b0 N
b0 n
10
#160000
00
#165000
0!
b10001 1
10
#170000
00
#175000
b10010 1
10
