RTL/Day12/Controller/controller_fsm.v
module controller_fsm(

    input wire clk,

    input wire reset,


    input wire start,


    output reg load_weight,

    output reg compute,

    output reg output_valid,

    output reg clear_acc


);



parameter IDLE = 3'd0;

parameter LOAD_WEIGHT = 3'd1;

parameter COMPUTE = 3'd2;

parameter OUTPUT = 3'd3;

parameter CLEAR = 3'd4;



reg [2:0] state;


always @(posedge clk)

begin


    if(reset)

        state <= IDLE;



    else begin


        case(state)


        IDLE:

        begin

            if(start)

                state <= LOAD_WEIGHT;

        end



        LOAD_WEIGHT:

            state <= COMPUTE;



        COMPUTE:

            state <= OUTPUT;



        OUTPUT:

            state <= CLEAR;



        CLEAR:

            state <= IDLE;



        default:

            state <= IDLE;


        endcase



    end


end






always @(*)

begin


    load_weight = 0;

    compute = 0;

    output_valid = 0;

    clear_acc = 0;



    case(state)


    LOAD_WEIGHT:

        load_weight = 1;



    COMPUTE:

        compute = 1;



    OUTPUT:

        output_valid = 1;



    CLEAR:

        clear_acc = 1;



    endcase


end



endmodule

Testbench/Day12/controller_fsm_tb.v
`timescale 1ns/1ps


module controller_fsm_tb;


reg clk;

reg reset;

reg start;


wire load_weight;

wire compute;

wire output_valid;

wire clear_acc;



controller_fsm dut
(

    .clk(clk),

    .reset(reset),

    .start(start),

    .load_weight(load_weight),

    .compute(compute),

    .output_valid(output_valid),

    .clear_acc(clear_acc)

);





always #5 clk = ~clk;




initial begin


    $dumpfile("controller_fsm.vcd");

    $dumpvars(0,controller_fsm_tb);



    clk = 0;

    reset = 1;

    start = 0;



    //----------------
    // reset
    //----------------

    #20;

    reset = 0;



    //----------------
    // start pulse
    //----------------

    #10;

    start = 1;


    #10;

    start = 0;



    //----------------
    // observe FSM
    //----------------


    #80;



    $finish;


end




always @(posedge clk)

begin

    $display(
    "time=%0t load=%b compute=%b output=%b clear=%b",
    $time,
    load_weight,
    compute,
    output_valid,
    clear_acc
    );

end



endmodule

Simulation/Day12/controller_fsm.vcd
$date
	Tue Aug  4 11:24:44 2026
$end
$version
	Icarus Verilog
$end
$timescale
	1ps
$end
$scope module controller_fsm_tb $end
$var wire 1 ! output_valid $end
$var wire 1 " load_weight $end
$var wire 1 # compute $end
$var wire 1 $ clear_acc $end
$var reg 1 % clk $end
$var reg 1 & reset $end
$var reg 1 ' start $end
$scope module dut $end
$var wire 1 % clk $end
$var wire 1 & reset $end
$var wire 1 ' start $end
$var parameter 3 ( CLEAR $end
$var parameter 3 ) COMPUTE $end
$var parameter 3 * IDLE $end
$var parameter 3 + LOAD_WEIGHT $end
$var parameter 3 , OUTPUT $end
$var reg 1 $ clear_acc $end
$var reg 1 # compute $end
$var reg 1 " load_weight $end
$var reg 1 ! output_valid $end
$var reg 3 - state [2:0] $end
$upscope $end
$upscope $end
$enddefinitions $end
$comment Show the parameter values. $end
$dumpall
b11 ,
b1 +
b0 *
b10 )
b100 (
$end
#0
$dumpvars
bx -
0'
1&
0%
x$
x#
x"
x!
$end
#5000
0$
0!
0#
0"
b0 -
1%
#10000
0%
#15000
1%
#20000
0%
0&
#25000
1%
#30000
0%
1'
#35000
1"
b1 -
1%
#40000
0%
0'
#45000
1#
0"
b10 -
1%
#50000
0%
#55000
1!
0#
b11 -
1%
#60000
0%
#65000
1$
0!
b100 -
1%
#70000
0%
#75000
0$
b0 -
1%
