RTL/Day12/pe_unit.v
module pe_unit #(

    parameter DATA_WIDTH = 8,
    parameter ACC_WIDTH  = 32

)(

    input wire clk,

    input wire reset,


    // control

    input wire enable,

    input wire clear_acc,


    // data

    input wire signed [DATA_WIDTH-1:0] activation_in,

    input wire signed [DATA_WIDTH-1:0] weight_in,



    // forwarding

    output reg signed [DATA_WIDTH-1:0] activation_out,

    output reg signed [DATA_WIDTH-1:0] weight_out,



    // accumulated result

    output reg signed [ACC_WIDTH-1:0] psum_out


);



    wire signed [(2*DATA_WIDTH)-1:0] product;


    assign product = activation_in * weight_in;



    reg signed [ACC_WIDTH-1:0] accumulator;



    always @(posedge clk) begin


        if(reset) begin


            activation_out <= 0;

            weight_out <= 0;

            accumulator <= 0;

            psum_out <= 0;


        end



        else begin



            // data forwarding

            activation_out <= activation_in;

            weight_out <= weight_in;



            // clear tile accumulation

            if(clear_acc) begin


                accumulator <= 0;


            end



            // MAC

            else if(enable) begin


                accumulator <=
                accumulator + product;


            end



            // output

            psum_out <= accumulator;


        end


    end



endmodule

Testbench/Day12/pe_unit_tb.v
`timescale 1ns/1ps


module pe_unit_tb;


parameter DATA_WIDTH = 8;

parameter ACC_WIDTH = 32;



reg clk;

reg reset;


reg enable;

reg clear_acc;



reg signed [DATA_WIDTH-1:0] activation_in;

reg signed [DATA_WIDTH-1:0] weight_in;



wire signed [DATA_WIDTH-1:0] activation_out;

wire signed [DATA_WIDTH-1:0] weight_out;


wire signed [ACC_WIDTH-1:0] psum_out;





pe_unit #(

    .DATA_WIDTH(DATA_WIDTH),

    .ACC_WIDTH(ACC_WIDTH)

)

dut

(

    .clk(clk),

    .reset(reset),


    .enable(enable),

    .clear_acc(clear_acc),



    .activation_in(activation_in),

    .weight_in(weight_in),



    .activation_out(activation_out),

    .weight_out(weight_out),



    .psum_out(psum_out)

);





always #5 clk=~clk;




initial begin


    $dumpfile("pe_unit.vcd");

    $dumpvars(0,pe_unit_tb);



    clk=0;


    reset=1;


    enable=0;

    clear_acc=0;


    activation_in=0;

    weight_in=0;



    // reset

    #20;


    reset=0;



    // clear accumulator

    clear_acc=1;


    #10;


    clear_acc=0;



    // ===================
    // MAC 1
    //
    // 3*4=12
    //
    // ===================


    enable=1;


    activation_in=3;

    weight_in=4;



    #10;



    // ===================
    // MAC 2
    //
    // 2*5=10
    //
    // total=22
    //
    // ===================


    activation_in=2;

    weight_in=5;



    #10;


    enable=0;



    #10;



    $display("----------------");

    $display("psum=%d",psum_out);

    $display("----------------");



    if(psum_out==22)

        $display("PE TEST PASS");

    else

        $display("PE TEST FAIL");



    $finish;


end



endmodule

Simulation/Day12/pe_unit.vcd
$date
	Tue Aug  4 10:44:16 2026
$end
$version
	Icarus Verilog
$end
$timescale
	1ps
$end
$scope module pe_unit_tb $end
$var wire 8 ! weight_out [7:0] $end
$var wire 32 " psum_out [31:0] $end
$var wire 8 # activation_out [7:0] $end
$var parameter 32 $ ACC_WIDTH $end
$var parameter 32 % DATA_WIDTH $end
$var reg 8 & activation_in [7:0] $end
$var reg 1 ' clear_acc $end
$var reg 1 ( clk $end
$var reg 1 ) enable $end
$var reg 1 * reset $end
$var reg 8 + weight_in [7:0] $end
$scope module dut $end
$var wire 8 , activation_in [7:0] $end
$var wire 1 ' clear_acc $end
$var wire 1 ( clk $end
$var wire 1 ) enable $end
$var wire 1 * reset $end
$var wire 8 - weight_in [7:0] $end
$var wire 16 . product [15:0] $end
$var parameter 32 / ACC_WIDTH $end
$var parameter 32 0 DATA_WIDTH $end
$var reg 32 1 accumulator [31:0] $end
$var reg 8 2 activation_out [7:0] $end
$var reg 32 3 psum_out [31:0] $end
$var reg 8 4 weight_out [7:0] $end
$upscope $end
$upscope $end
$enddefinitions $end
$comment Show the parameter values. $end
$dumpall
b1000 0
b100000 /
b1000 %
b100000 $
$end
#0
$dumpvars
bx 4
bx 3
bx 2
bx 1
b0 .
b0 -
b0 ,
b0 +
1*
0)
0(
0'
b0 &
bx #
bx "
bx !
$end
#5000
b0 "
b0 3
b0 1
b0 !
b0 4
b0 #
b0 2
1(
#10000
0(
#15000
1(
#20000
0(
1'
0*
#25000
1(
#30000
0(
b1100 .
b100 +
b100 -
b11 &
b11 ,
1)
0'
#35000
b1100 1
b100 !
b100 4
b11 #
b11 2
1(
#40000
0(
b101 +
b101 -
b1010 .
b10 &
b10 ,
#45000
b1100 "
b1100 3
b10110 1
b101 !
b101 4
b10 #
b10 2
1(
#50000
0(
0)
#55000
b10110 "
b10110 3
1(
