RTL/Day12/pe_unit.v
module pe_unit #(

    parameter DATA_WIDTH = 8,
    parameter ACC_WIDTH  = 32

)(

    input wire clk,

    input wire reset,


    // control

    input wire enable,

    input wire clear_acc,


    // data

    input wire signed [DATA_WIDTH-1:0] activation_in,

    input wire signed [DATA_WIDTH-1:0] weight_in,



    // forwarding

    output reg signed [DATA_WIDTH-1:0] activation_out,

    output reg signed [DATA_WIDTH-1:0] weight_out,



    // accumulated result

    output reg signed [ACC_WIDTH-1:0] psum_out


);



    wire signed [(2*DATA_WIDTH)-1:0] product;


    assign product = activation_in * weight_in;



    reg signed [ACC_WIDTH-1:0] accumulator;



    always @(posedge clk) begin


        if(reset) begin


            activation_out <= 0;

            weight_out <= 0;

            accumulator <= 0;

            psum_out <= 0;


        end



        else begin



            // data forwarding

            activation_out <= activation_in;

            weight_out <= weight_in;



            // clear tile accumulation

            if(clear_acc) begin


                accumulator <= 0;


            end



            // MAC

            else if(enable) begin


                accumulator <=
                accumulator + product;


            end



            // output

            psum_out <= accumulator;


        end


    end



endmodule

RTL/Day12/systolic_array_4x4.v
module systolic_array_4x4 #(

    parameter DATA_WIDTH = 8,
    parameter ACC_WIDTH  = 32

)(


    input wire clk,

    input wire reset,


    input wire enable,

    input wire clear_acc,


    input wire signed [DATA_WIDTH-1:0]
    activation_in [0:3],


    input wire signed [DATA_WIDTH-1:0]
    weight_in [0:3],



    output wire signed [ACC_WIDTH-1:0]
    result [0:3][0:3]

);




    // Activation horizontal path

    wire signed [DATA_WIDTH-1:0]
    activation_wire [0:3][0:4];



    // Weight vertical path

    wire signed [DATA_WIDTH-1:0]
    weight_wire [0:4][0:3];






    // -----------------------------
    // Input connection
    // -----------------------------


    genvar i;


    generate

        for(i=0;i<4;i=i+1)

        begin: INPUT


            assign activation_wire[i][0]
            =
            activation_in[i];


        end

    endgenerate





    genvar c;


    generate

        for(c=0;c<4;c=c+1)

        begin: WEIGHT_INPUT


            assign weight_wire[0][c]
            =
            weight_in[c];


        end

    endgenerate






    // -----------------------------
    // PE Array
    // -----------------------------


    genvar row;
    genvar col;



    generate


        for(row=0;row<4;row=row+1)

        begin: ROW


            for(col=0;col<4;col=col+1)

            begin: COL



                pe_unit #(

                    .DATA_WIDTH(DATA_WIDTH),

                    .ACC_WIDTH(ACC_WIDTH)

                )

                pe_inst

                (

                    .clk(clk),

                    .reset(reset),


                    .enable(enable),

                    .clear_acc(clear_acc),



                    .activation_in(
                        activation_wire[row][col]
                    ),



                    .weight_in(
                        weight_wire[row][col]
                    ),




                    .activation_out(
                        activation_wire[row][col+1]
                    ),



                    .weight_out(
                        weight_wire[row+1][col]
                    ),



                    .psum_out(
                        result[row][col]
                    )


                );


            end


        end


    endgenerate




endmodule

Testbench/Day12/systolic_array_tb.v
`timescale 1ns/1ps


module systolic_array_tb;


parameter DATA_WIDTH = 8;
parameter ACC_WIDTH  = 32;



reg clk;

reg reset;

reg enable;

reg clear_acc;



reg signed [DATA_WIDTH-1:0]
activation_in [0:3];


reg signed [DATA_WIDTH-1:0]
weight_in [0:3];



wire signed [ACC_WIDTH-1:0]
result [0:3][0:3];





//================================================
// DUT
//================================================

systolic_array_4x4 #(


    .DATA_WIDTH(DATA_WIDTH),

    .ACC_WIDTH(ACC_WIDTH)


)

dut

(

    .clk(clk),

    .reset(reset),


    .enable(enable),

    .clear_acc(clear_acc),


    .activation_in(activation_in),

    .weight_in(weight_in),


    .result(result)

);





//================================================
// Clock
//================================================

always #5 clk = ~clk;



integer i;



//================================================
// Test
//================================================

initial begin


    //------------------------------------------------
    // waveform
    //------------------------------------------------

    $dumpfile("systolic_array.vcd");

    $dumpvars(0,systolic_array_tb);




    //------------------------------------------------
    // Initial state
    //------------------------------------------------

    clk = 0;

    reset = 1;

    enable = 0;

    clear_acc = 0;



    for(i=0;i<4;i=i+1)

    begin

        activation_in[i]=0;

        weight_in[i]=0;

    end





    //------------------------------------------------
    // Reset
    //------------------------------------------------

    #20;


    reset = 0;




    //------------------------------------------------
    // Clear accumulator
    //------------------------------------------------

    clear_acc = 1;


    #10;


    clear_acc = 0;





    //------------------------------------------------
    // Enable PE array
    //------------------------------------------------

    enable = 1;





    //------------------------------------------------
    // Inject data into all rows and columns
    //
    // Activation:
    //
    // row0 = 2
    // row1 = 2
    // row2 = 2
    // row3 = 2
    //
    //
    // Weight:
    //
    // col0 = 3
    // col1 = 3
    // col2 = 3
    // col3 = 3
    //
    //
    // Every PE receives:
    //
    // 2 * 3 = 6
    //
    //------------------------------------------------


    activation_in[0]=2;

    activation_in[1]=2;

    activation_in[2]=2;

    activation_in[3]=2;



    weight_in[0]=3;

    weight_in[1]=3;

    weight_in[2]=3;

    weight_in[3]=3;




    //------------------------------------------------
    // Hold input
    //------------------------------------------------


    repeat(6)

    begin

        #10;

    end





    //------------------------------------------------
    // Stop input
    //------------------------------------------------


    for(i=0;i<4;i=i+1)

    begin

        activation_in[i]=0;

        weight_in[i]=0;

    end




    //------------------------------------------------
    // Pipeline flush
    //------------------------------------------------


    #120;





    //------------------------------------------------
    // Display
    //------------------------------------------------


    $display("--------------------------------");

    $display("PE00 = %d",result[0][0]);

    $display("PE01 = %d",result[0][1]);

    $display("PE10 = %d",result[1][0]);

    $display("PE11 = %d",result[1][1]);

    $display("--------------------------------");





    //------------------------------------------------
    // Check
    //------------------------------------------------


    if(result[0][0] > 0)

        $display("PE00 PASS");

    else

        $display("PE00 FAIL");



    if(result[0][1] > 0)

        $display("PE01 PASS");

    else

        $display("PE01 FAIL");



    if(result[1][0] > 0)

        $display("PE10 PASS");

    else

        $display("PE10 FAIL");




    $finish;


end



endmodule

Simulation/Day12/systolic_array.vcd
$date
	Tue Aug  4 11:19:25 2026
$end
$version
	Icarus Verilog
$end
$timescale
	1ps
$end
$scope module systolic_array_tb $end
$var parameter 32 ! ACC_WIDTH $end
$var parameter 32 " DATA_WIDTH $end
$var reg 1 # clear_acc $end
$var reg 1 $ clk $end
$var reg 1 % enable $end
$var reg 1 & reset $end
$var integer 32 ' i [31:0] $end
$scope module dut $end
$var wire 1 # clear_acc $end
$var wire 1 $ clk $end
$var wire 1 % enable $end
$var wire 1 & reset $end
$var parameter 32 ( ACC_WIDTH $end
$var parameter 32 ) DATA_WIDTH $end
$scope begin INPUT[0] $end
$var parameter 2 * i $end
$upscope $end
$scope begin INPUT[1] $end
$var parameter 2 + i $end
$upscope $end
$scope begin INPUT[2] $end
$var parameter 3 , i $end
$upscope $end
$scope begin INPUT[3] $end
$var parameter 3 - i $end
$upscope $end
$scope begin ROW[0] $end
$var parameter 2 . row $end
$scope begin COL[0] $end
$var parameter 2 / col $end
$scope module pe_inst $end
$var wire 8 0 activation_in [7:0] $end
$var wire 1 # clear_acc $end
$var wire 1 $ clk $end
$var wire 1 % enable $end
$var wire 1 & reset $end
$var wire 8 1 weight_in [7:0] $end
$var wire 16 2 product [15:0] $end
$var parameter 32 3 ACC_WIDTH $end
$var parameter 32 4 DATA_WIDTH $end
$var reg 32 5 accumulator [31:0] $end
$var reg 8 6 activation_out [7:0] $end
$var reg 32 7 psum_out [31:0] $end
$var reg 8 8 weight_out [7:0] $end
$upscope $end
$upscope $end
$scope begin COL[1] $end
$var parameter 2 9 col $end
$scope module pe_inst $end
$var wire 8 : activation_in [7:0] $end
$var wire 1 # clear_acc $end
$var wire 1 $ clk $end
$var wire 1 % enable $end
$var wire 1 & reset $end
$var wire 8 ; weight_in [7:0] $end
$var wire 16 < product [15:0] $end
$var parameter 32 = ACC_WIDTH $end
$var parameter 32 > DATA_WIDTH $end
$var reg 32 ? accumulator [31:0] $end
$var reg 8 @ activation_out [7:0] $end
$var reg 32 A psum_out [31:0] $end
$var reg 8 B weight_out [7:0] $end
$upscope $end
$upscope $end
$scope begin COL[2] $end
$var parameter 3 C col $end
$scope module pe_inst $end
$var wire 8 D activation_in [7:0] $end
$var wire 1 # clear_acc $end
$var wire 1 $ clk $end
$var wire 1 % enable $end
$var wire 1 & reset $end
$var wire 8 E weight_in [7:0] $end
$var wire 16 F product [15:0] $end
$var parameter 32 G ACC_WIDTH $end
$var parameter 32 H DATA_WIDTH $end
$var reg 32 I accumulator [31:0] $end
$var reg 8 J activation_out [7:0] $end
$var reg 32 K psum_out [31:0] $end
$var reg 8 L weight_out [7:0] $end
$upscope $end
$upscope $end
$scope begin COL[3] $end
$var parameter 3 M col $end
$scope module pe_inst $end
$var wire 8 N activation_in [7:0] $end
$var wire 1 # clear_acc $end
$var wire 1 $ clk $end
$var wire 1 % enable $end
$var wire 1 & reset $end
$var wire 8 O weight_in [7:0] $end
$var wire 16 P product [15:0] $end
$var parameter 32 Q ACC_WIDTH $end
$var parameter 32 R DATA_WIDTH $end
$var reg 32 S accumulator [31:0] $end
$var reg 8 T activation_out [7:0] $end
$var reg 32 U psum_out [31:0] $end
$var reg 8 V weight_out [7:0] $end
$upscope $end
$upscope $end
$upscope $end
$scope begin ROW[1] $end
$var parameter 2 W row $end
$scope begin COL[0] $end
$var parameter 2 X col $end
$scope module pe_inst $end
$var wire 8 Y activation_in [7:0] $end
$var wire 1 # clear_acc $end
$var wire 1 $ clk $end
$var wire 1 % enable $end
$var wire 1 & reset $end
$var wire 8 Z weight_in [7:0] $end
$var wire 16 [ product [15:0] $end
$var parameter 32 \ ACC_WIDTH $end
$var parameter 32 ] DATA_WIDTH $end
$var reg 32 ^ accumulator [31:0] $end
$var reg 8 _ activation_out [7:0] $end
$var reg 32 ` psum_out [31:0] $end
$var reg 8 a weight_out [7:0] $end
$upscope $end
$upscope $end
$scope begin COL[1] $end
$var parameter 2 b col $end
$scope module pe_inst $end
$var wire 8 c activation_in [7:0] $end
$var wire 1 # clear_acc $end
$var wire 1 $ clk $end
$var wire 1 % enable $end
$var wire 1 & reset $end
$var wire 8 d weight_in [7:0] $end
$var wire 16 e product [15:0] $end
$var parameter 32 f ACC_WIDTH $end
$var parameter 32 g DATA_WIDTH $end
$var reg 32 h accumulator [31:0] $end
$var reg 8 i activation_out [7:0] $end
$var reg 32 j psum_out [31:0] $end
$var reg 8 k weight_out [7:0] $end
$upscope $end
$upscope $end
$scope begin COL[2] $end
$var parameter 3 l col $end
$scope module pe_inst $end
$var wire 8 m activation_in [7:0] $end
$var wire 1 # clear_acc $end
$var wire 1 $ clk $end
$var wire 1 % enable $end
$var wire 1 & reset $end
$var wire 8 n weight_in [7:0] $end
$var wire 16 o product [15:0] $end
$var parameter 32 p ACC_WIDTH $end
$var parameter 32 q DATA_WIDTH $end
$var reg 32 r accumulator [31:0] $end
$var reg 8 s activation_out [7:0] $end
$var reg 32 t psum_out [31:0] $end
$var reg 8 u weight_out [7:0] $end
$upscope $end
$upscope $end
$scope begin COL[3] $end
$var parameter 3 v col $end
$scope module pe_inst $end
$var wire 8 w activation_in [7:0] $end
$var wire 1 # clear_acc $end
$var wire 1 $ clk $end
$var wire 1 % enable $end
$var wire 1 & reset $end
$var wire 8 x weight_in [7:0] $end
$var wire 16 y product [15:0] $end
$var parameter 32 z ACC_WIDTH $end
$var parameter 32 { DATA_WIDTH $end
$var reg 32 | accumulator [31:0] $end
$var reg 8 } activation_out [7:0] $end
$var reg 32 ~ psum_out [31:0] $end
$var reg 8 !" weight_out [7:0] $end
$upscope $end
$upscope $end
$upscope $end
$scope begin ROW[2] $end
$var parameter 3 "" row $end
$scope begin COL[0] $end
$var parameter 2 #" col $end
$scope module pe_inst $end
$var wire 8 $" activation_in [7:0] $end
$var wire 1 # clear_acc $end
$var wire 1 $ clk $end
$var wire 1 % enable $end
$var wire 1 & reset $end
$var wire 8 %" weight_in [7:0] $end
$var wire 16 &" product [15:0] $end
$var parameter 32 '" ACC_WIDTH $end
$var parameter 32 (" DATA_WIDTH $end
$var reg 32 )" accumulator [31:0] $end
$var reg 8 *" activation_out [7:0] $end
$var reg 32 +" psum_out [31:0] $end
$var reg 8 ," weight_out [7:0] $end
$upscope $end
$upscope $end
$scope begin COL[1] $end
$var parameter 2 -" col $end
$scope module pe_inst $end
$var wire 8 ." activation_in [7:0] $end
$var wire 1 # clear_acc $end
$var wire 1 $ clk $end
$var wire 1 % enable $end
$var wire 1 & reset $end
$var wire 8 /" weight_in [7:0] $end
$var wire 16 0" product [15:0] $end
$var parameter 32 1" ACC_WIDTH $end
$var parameter 32 2" DATA_WIDTH $end
$var reg 32 3" accumulator [31:0] $end
$var reg 8 4" activation_out [7:0] $end
$var reg 32 5" psum_out [31:0] $end
$var reg 8 6" weight_out [7:0] $end
$upscope $end
$upscope $end
$scope begin COL[2] $end
$var parameter 3 7" col $end
$scope module pe_inst $end
$var wire 8 8" activation_in [7:0] $end
$var wire 1 # clear_acc $end
$var wire 1 $ clk $end
$var wire 1 % enable $end
$var wire 1 & reset $end
$var wire 8 9" weight_in [7:0] $end
$var wire 16 :" product [15:0] $end
$var parameter 32 ;" ACC_WIDTH $end
$var parameter 32 <" DATA_WIDTH $end
$var reg 32 =" accumulator [31:0] $end
$var reg 8 >" activation_out [7:0] $end
$var reg 32 ?" psum_out [31:0] $end
$var reg 8 @" weight_out [7:0] $end
$upscope $end
$upscope $end
$scope begin COL[3] $end
$var parameter 3 A" col $end
$scope module pe_inst $end
$var wire 8 B" activation_in [7:0] $end
$var wire 1 # clear_acc $end
$var wire 1 $ clk $end
$var wire 1 % enable $end
$var wire 1 & reset $end
$var wire 8 C" weight_in [7:0] $end
$var wire 16 D" product [15:0] $end
$var parameter 32 E" ACC_WIDTH $end
$var parameter 32 F" DATA_WIDTH $end
$var reg 32 G" accumulator [31:0] $end
$var reg 8 H" activation_out [7:0] $end
$var reg 32 I" psum_out [31:0] $end
$var reg 8 J" weight_out [7:0] $end
$upscope $end
$upscope $end
$upscope $end
$scope begin ROW[3] $end
$var parameter 3 K" row $end
$scope begin COL[0] $end
$var parameter 2 L" col $end
$scope module pe_inst $end
$var wire 8 M" activation_in [7:0] $end
$var wire 1 # clear_acc $end
$var wire 1 $ clk $end
$var wire 1 % enable $end
$var wire 1 & reset $end
$var wire 8 N" weight_in [7:0] $end
$var wire 16 O" product [15:0] $end
$var parameter 32 P" ACC_WIDTH $end
$var parameter 32 Q" DATA_WIDTH $end
$var reg 32 R" accumulator [31:0] $end
$var reg 8 S" activation_out [7:0] $end
$var reg 32 T" psum_out [31:0] $end
$var reg 8 U" weight_out [7:0] $end
$upscope $end
$upscope $end
$scope begin COL[1] $end
$var parameter 2 V" col $end
$scope module pe_inst $end
$var wire 8 W" activation_in [7:0] $end
$var wire 1 # clear_acc $end
$var wire 1 $ clk $end
$var wire 1 % enable $end
$var wire 1 & reset $end
$var wire 8 X" weight_in [7:0] $end
$var wire 16 Y" product [15:0] $end
$var parameter 32 Z" ACC_WIDTH $end
$var parameter 32 [" DATA_WIDTH $end
$var reg 32 \" accumulator [31:0] $end
$var reg 8 ]" activation_out [7:0] $end
$var reg 32 ^" psum_out [31:0] $end
$var reg 8 _" weight_out [7:0] $end
$upscope $end
$upscope $end
$scope begin COL[2] $end
$var parameter 3 `" col $end
$scope module pe_inst $end
$var wire 8 a" activation_in [7:0] $end
$var wire 1 # clear_acc $end
$var wire 1 $ clk $end
$var wire 1 % enable $end
$var wire 1 & reset $end
$var wire 8 b" weight_in [7:0] $end
$var wire 16 c" product [15:0] $end
$var parameter 32 d" ACC_WIDTH $end
$var parameter 32 e" DATA_WIDTH $end
$var reg 32 f" accumulator [31:0] $end
$var reg 8 g" activation_out [7:0] $end
$var reg 32 h" psum_out [31:0] $end
$var reg 8 i" weight_out [7:0] $end
$upscope $end
$upscope $end
$scope begin COL[3] $end
$var parameter 3 j" col $end
$scope module pe_inst $end
$var wire 8 k" activation_in [7:0] $end
$var wire 1 # clear_acc $end
$var wire 1 $ clk $end
$var wire 1 % enable $end
$var wire 1 & reset $end
$var wire 8 l" weight_in [7:0] $end
$var wire 16 m" product [15:0] $end
$var parameter 32 n" ACC_WIDTH $end
$var parameter 32 o" DATA_WIDTH $end
$var reg 32 p" accumulator [31:0] $end
$var reg 8 q" activation_out [7:0] $end
$var reg 32 r" psum_out [31:0] $end
$var reg 8 s" weight_out [7:0] $end
$upscope $end
$upscope $end
$upscope $end
$scope begin WEIGHT_INPUT[0] $end
$var parameter 2 t" c $end
$upscope $end
$scope begin WEIGHT_INPUT[1] $end
$var parameter 2 u" c $end
$upscope $end
$scope begin WEIGHT_INPUT[2] $end
$var parameter 3 v" c $end
$upscope $end
$scope begin WEIGHT_INPUT[3] $end
$var parameter 3 w" c $end
$upscope $end
$upscope $end
$upscope $end
$enddefinitions $end
$comment Show the parameter values. $end
$dumpall
b11 w"
b10 v"
b1 u"
b0 t"
b1000 o"
b100000 n"
b11 j"
b1000 e"
b100000 d"
b10 `"
b1000 ["
b100000 Z"
b1 V"
b1000 Q"
b100000 P"
b0 L"
b11 K"
b1000 F"
b100000 E"
b11 A"
b1000 <"
b100000 ;"
b10 7"
b1000 2"
b100000 1"
b1 -"
b1000 ("
b100000 '"
b0 #"
b10 ""
b1000 {
b100000 z
b11 v
b1000 q
b100000 p
b10 l
b1000 g
b100000 f
b1 b
b1000 ]
b100000 \
b0 X
b1 W
b1000 R
b100000 Q
b11 M
b1000 H
b100000 G
b10 C
b1000 >
b100000 =
b1 9
b1000 4
b100000 3
b0 /
b0 .
b11 -
b10 ,
b1 +
b0 *
b1000 )
b100000 (
b1000 "
b100000 !
$end
#0
$dumpvars
bx s"
bx r"
bx q"
bx p"
bx m"
bx l"
bx k"
bx i"
bx h"
bx g"
bx f"
bx c"
bx b"
bx a"
bx _"
bx ^"
bx ]"
bx \"
bx Y"
bx X"
bx W"
bx U"
bx T"
bx S"
bx R"
bx O"
bx N"
b0 M"
bx J"
bx I"
bx H"
bx G"
bx D"
bx C"
bx B"
bx @"
bx ?"
bx >"
bx ="
bx :"
bx 9"
bx 8"
bx 6"
bx 5"
bx 4"
bx 3"
bx 0"
bx /"
bx ."
bx ,"
bx +"
bx *"
bx )"
bx &"
bx %"
b0 $"
bx !"
bx ~
bx }
bx |
bx y
bx x
bx w
bx u
bx t
bx s
bx r
bx o
bx n
bx m
bx k
bx j
bx i
bx h
bx e
bx d
bx c
bx a
bx `
bx _
bx ^
bx [
bx Z
b0 Y
bx V
bx U
bx T
bx S
bx P
b0 O
bx N
bx L
bx K
bx J
bx I
bx F
b0 E
bx D
bx B
bx A
bx @
bx ?
bx <
b0 ;
bx :
bx 8
bx 7
bx 6
bx 5
b0 2
b0 1
b0 0
b100 '
1&
0%
0$
0#
$end
#5000
b0 7
b0 5
b0 [
b0 8
b0 Z
b0 <
b0 6
b0 :
b0 A
b0 ?
b0 e
b0 B
b0 d
b0 F
b0 @
b0 D
b0 K
b0 I
b0 o
b0 L
b0 n
b0 P
b0 J
b0 N
b0 U
b0 S
b0 y
b0 V
b0 x
b0 T
b0 `
b0 ^
b0 &"
b0 a
b0 %"
b0 _
b0 c
b0 j
b0 h
b0 0"
b0 k
b0 /"
b0 i
b0 m
b0 t
b0 r
b0 :"
b0 u
b0 9"
b0 s
b0 w
b0 ~
b0 |
b0 D"
b0 !"
b0 C"
b0 }
b0 +"
b0 )"
b0 O"
b0 ,"
b0 N"
b0 *"
b0 ."
b0 5"
b0 3"
b0 Y"
b0 6"
b0 X"
b0 4"
b0 8"
b0 ?"
b0 ="
b0 c"
b0 @"
b0 b"
b0 >"
b0 B"
b0 I"
b0 G"
b0 m"
b0 J"
b0 l"
b0 H"
b0 T"
b0 R"
b0 U"
b0 S"
b0 W"
b0 ^"
b0 \"
b0 _"
b0 ]"
b0 a"
b0 h"
b0 f"
b0 i"
b0 g"
b0 k"
b0 r"
b0 p"
b0 s"
b0 q"
1$
#10000
0$
#15000
1$
#20000
0$
1#
0&
#25000
1$
#30000
0$
b11 O
b11 E
b11 ;
b110 2
b11 1
b10 M"
b10 $"
b10 Y
b10 0
1%
0#
#35000
b10 S"
b10 W"
b10 *"
b10 ."
b110 e
b10 _
b10 c
b11 V
b11 x
b11 L
b11 n
b11 B
b11 d
b110 5
b110 [
b11 8
b11 Z
b110 <
b10 6
b10 :
1$
#40000
0$
#45000
b110 7
b1100 5
b110 ?
b110 F
b10 @
b10 D
b110 ^
b110 &"
b11 a
b11 %"
b110 h
b110 0"
b11 k
b11 /"
b110 o
b10 i
b10 m
b110 :"
b11 u
b11 9"
b11 !"
b11 C"
b10 4"
b10 8"
b10 ]"
b10 a"
1$
#50000
0$
#55000
b110 m"
b10 g"
b10 k"
b11 J"
b11 l"
b110 ="
b110 c"
b11 @"
b11 b"
b110 D"
b10 >"
b10 B"
b110 3"
b110 Y"
b11 6"
b11 X"
b110 )"
b110 O"
b11 ,"
b11 N"
b110 r
b110 y
b10 s
b10 w
b110 j
b1100 h
b110 `
b1100 ^
b110 I
b110 P
b10 J
b10 N
b110 A
b1100 ?
b1100 7
b10010 5
1$
#60000
0$
#65000
b10010 7
b11000 5
b1100 A
b10010 ?
b110 K
b1100 I
b110 S
b10 T
b1100 `
b10010 ^
b1100 j
b10010 h
b110 t
b1100 r
b110 |
b10 }
b110 +"
b1100 )"
b110 5"
b1100 3"
b110 ?"
b1100 ="
b110 G"
b10 H"
b110 R"
b11 U"
b110 \"
b11 _"
b110 f"
b11 i"
b110 p"
b11 s"
b10 q"
1$
#70000
0$
#75000
b110 r"
b1100 p"
b110 h"
b1100 f"
b110 ^"
b1100 \"
b110 T"
b1100 R"
b110 I"
b1100 G"
b1100 ?"
b10010 ="
b1100 5"
b10010 3"
b1100 +"
b10010 )"
b110 ~
b1100 |
b1100 t
b10010 r
b10010 j
b11000 h
b10010 `
b11000 ^
b110 U
b1100 S
b1100 K
b10010 I
b10010 A
b11000 ?
b11000 7
b11110 5
1$
#80000
0$
#85000
b11110 7
b100100 5
b11000 A
b11110 ?
b10010 K
b11000 I
b1100 U
b10010 S
b11000 `
b11110 ^
b11000 j
b11110 h
b10010 t
b11000 r
b1100 ~
b10010 |
b10010 +"
b11000 )"
b10010 5"
b11000 3"
b10010 ?"
b11000 ="
b1100 I"
b10010 G"
b1100 T"
b10010 R"
b1100 ^"
b10010 \"
b1100 h"
b10010 f"
b1100 r"
b10010 p"
1$
#90000
0$
b0 P
b0 O
b0 O"
b0 M"
b0 F
b0 E
b0 &"
b0 $"
b0 <
b0 ;
b0 [
b0 Y
b0 1
b0 2
b0 0
b100 '
#95000
b10010 r"
b11000 p"
b10010 h"
b11000 f"
b10010 ^"
b11000 \"
b10010 T"
b0 Y"
b0 S"
b0 W"
b10010 I"
b11000 G"
b11000 ?"
b11110 ="
b11000 5"
b11110 3"
b11000 +"
b0 0"
b0 *"
b0 ."
b10010 ~
b11000 |
b11000 t
b11110 r
b11110 j
b100100 h
b11110 `
b0 _
b0 c
b10010 U
b0 y
b0 V
b0 x
b11000 K
b0 o
b0 L
b0 n
b11110 A
b0 e
b0 B
b0 d
b100100 7
b0 8
b0 Z
b0 6
b0 :
1$
#100000
0$
#105000
b0 @
b0 D
b0 a
b0 %"
b100100 j
b0 k
b0 /"
b0 i
b0 m
b11110 t
b0 u
b0 9"
b11000 ~
b0 D"
b0 !"
b0 C"
b11110 5"
b0 :"
b0 4"
b0 8"
b11110 ?"
b100100 ="
b11000 I"
b11110 G"
b11000 ^"
b0 c"
b0 ]"
b0 a"
b11000 h"
b11110 f"
b11000 r"
b11110 p"
1$
#110000
0$
#115000
b11110 r"
b100100 p"
b11110 h"
b0 g"
b0 k"
b11110 I"
b0 m"
b0 J"
b0 l"
b100100 ?"
b0 @"
b0 b"
b0 >"
b0 B"
b0 6"
b0 X"
b0 ,"
b0 N"
b0 s
b0 w
b0 J
b0 N
1$
#120000
0$
#125000
b0 T
b0 }
b0 H"
b0 U"
b0 _"
b0 i"
b100100 r"
b0 s"
b0 q"
1$
