RTL/Day12/pe_unit.v
module pe_unit #(

    parameter DATA_WIDTH = 8,
    parameter ACC_WIDTH  = 32

)(

    input wire clk,

    input wire reset,


    // control

    input wire enable,

    input wire clear_acc,


    // data

    input wire signed [DATA_WIDTH-1:0] activation_in,

    input wire signed [DATA_WIDTH-1:0] weight_in,



    // forwarding

    output reg signed [DATA_WIDTH-1:0] activation_out,

    output reg signed [DATA_WIDTH-1:0] weight_out,



    // accumulated result

    output reg signed [ACC_WIDTH-1:0] psum_out


);



    wire signed [(2*DATA_WIDTH)-1:0] product;


    assign product = activation_in * weight_in;



    reg signed [ACC_WIDTH-1:0] accumulator;



    always @(posedge clk) begin


        if(reset) begin


            activation_out <= 0;

            weight_out <= 0;

            accumulator <= 0;

            psum_out <= 0;


        end



        else begin



            // data forwarding

            activation_out <= activation_in;

            weight_out <= weight_in;



            // clear tile accumulation

            if(clear_acc) begin


                accumulator <= 0;


            end



            // MAC

            else if(enable) begin


                accumulator <=
                accumulator + product;


            end



            // output

            psum_out <= accumulator;


        end


    end



endmodule

RTL/Day12/systolic_array_4x4.v
module systolic_array_4x4 #(

    parameter DATA_WIDTH = 8,
    parameter ACC_WIDTH  = 32

)(


    input wire clk,

    input wire reset,


    input wire enable,

    input wire clear_acc,


    input wire signed [DATA_WIDTH-1:0]
    activation_in [0:3],


    input wire signed [DATA_WIDTH-1:0]
    weight_in [0:3],



    output wire signed [ACC_WIDTH-1:0]
    result [0:3][0:3]

);




    // Activation horizontal path

    wire signed [DATA_WIDTH-1:0]
    activation_wire [0:3][0:4];



    // Weight vertical path

    wire signed [DATA_WIDTH-1:0]
    weight_wire [0:4][0:3];






    // -----------------------------
    // Input connection
    // -----------------------------


    genvar i;


    generate

        for(i=0;i<4;i=i+1)

        begin: INPUT


            assign activation_wire[i][0]
            =
            activation_in[i];


        end

    endgenerate





    genvar c;


    generate

        for(c=0;c<4;c=c+1)

        begin: WEIGHT_INPUT


            assign weight_wire[0][c]
            =
            weight_in[c];


        end

    endgenerate






    // -----------------------------
    // PE Array
    // -----------------------------


    genvar row;
    genvar col;



    generate


        for(row=0;row<4;row=row+1)

        begin: ROW


            for(col=0;col<4;col=col+1)

            begin: COL



                pe_unit #(

                    .DATA_WIDTH(DATA_WIDTH),

                    .ACC_WIDTH(ACC_WIDTH)

                )

                pe_inst

                (

                    .clk(clk),

                    .reset(reset),


                    .enable(enable),

                    .clear_acc(clear_acc),



                    .activation_in(
                        activation_wire[row][col]
                    ),



                    .weight_in(
                        weight_wire[row][col]
                    ),




                    .activation_out(
                        activation_wire[row][col+1]
                    ),



                    .weight_out(
                        weight_wire[row+1][col]
                    ),



                    .psum_out(
                        result[row][col]
                    )


                );


            end


        end


    endgenerate




endmodule

Testbench/Day12/systolic_array_tb.v
`timescale 1ns/1ps


module systolic_array_tb;


parameter DATA_WIDTH = 8;

parameter ACC_WIDTH = 32;



reg clk;

reg reset;

reg enable;

reg clear_acc;



reg signed [DATA_WIDTH-1:0]
activation_in [0:3];


reg signed [DATA_WIDTH-1:0]
weight_in [0:3];



wire signed [ACC_WIDTH-1:0]
result [0:3][0:3];





systolic_array_4x4 #(


    .DATA_WIDTH(DATA_WIDTH),

    .ACC_WIDTH(ACC_WIDTH)


)

dut

(

    .clk(clk),

    .reset(reset),


    .enable(enable),

    .clear_acc(clear_acc),


    .activation_in(activation_in),

    .weight_in(weight_in),


    .result(result)

);





always #5 clk = ~clk;



integer i;



initial begin



    $dumpfile("systolic_array.vcd");

    $dumpvars(0,systolic_array_tb);




    clk=0;


    reset=1;


    enable=0;

    clear_acc=0;



    for(i=0;i<4;i=i+1)

    begin

        activation_in[i]=0;

        weight_in[i]=0;

    end




    // --------------------
    // Reset
    // --------------------

    #20;


    reset=0;



    // --------------------
    // Clear accumulator
    // --------------------

    clear_acc=1;


    #10;


    clear_acc=0;




    // --------------------
    // Load weights
    //
    // B:
    //
    // [5 6]
    // [7 8]
    //
    // --------------------


    weight_in[0]=5;

    weight_in[1]=7;


    #10;



    // --------------------
    // Feed activations
    //
    // A:
    //
    // [1 2]
    // [3 4]
    //
    // --------------------


    enable=1;



    // Row0

    activation_in[0]=1;


    #10;


    activation_in[0]=2;


    #10;


    activation_in[0]=0;



    // Row1


    activation_in[1]=3;


    #10;


    activation_in[1]=4;


    #10;


    activation_in[1]=0;




    // wait pipeline


    #50;



    enable=0;




    $display("---------------------");


    $display("C00 = %d",result[0][0]);

    $display("C01 = %d",result[0][1]);

    $display("C10 = %d",result[1][0]);

    $display("C11 = %d",result[1][1]);


    $display("---------------------");





    if(result[0][0]==19)

        $display("C00 PASS");

    else

        $display("C00 FAIL");





    if(result[0][1]==22)

        $display("C01 PASS");

    else

        $display("C01 FAIL");





    if(result[1][0]==43)

        $display("C10 PASS");

    else

        $display("C10 FAIL");





    if(result[1][1]==50)

        $display("C11 PASS");

    else

        $display("C11 FAIL");





    $finish;



end



endmodule

Simulation/Day12/systolic_array.vcd
$date
	Mon Aug  3 12:06:21 2026
$end
$version
	Icarus Verilog
$end
$timescale
	1ps
$end
$scope module systolic_array_tb $end
$var parameter 32 ! ACC_WIDTH $end
$var parameter 32 " DATA_WIDTH $end
$var reg 1 # clear_acc $end
$var reg 1 $ clk $end
$var reg 1 % enable $end
$var reg 1 & reset $end
$var integer 32 ' i [31:0] $end
$scope module dut $end
$var wire 1 # clear_acc $end
$var wire 1 $ clk $end
$var wire 1 % enable $end
$var wire 1 & reset $end
$var parameter 32 ( ACC_WIDTH $end
$var parameter 32 ) DATA_WIDTH $end
$scope begin INPUT[0] $end
$var parameter 2 * i $end
$upscope $end
$scope begin INPUT[1] $end
$var parameter 2 + i $end
$upscope $end
$scope begin INPUT[2] $end
$var parameter 3 , i $end
$upscope $end
$scope begin INPUT[3] $end
$var parameter 3 - i $end
$upscope $end
$scope begin ROW[0] $end
$var parameter 2 . row $end
$scope begin COL[0] $end
$var parameter 2 / col $end
$scope module pe_inst $end
$var wire 8 0 activation_in [7:0] $end
$var wire 1 # clear_acc $end
$var wire 1 $ clk $end
$var wire 1 % enable $end
$var wire 1 & reset $end
$var wire 8 1 weight_in [7:0] $end
$var wire 16 2 product [15:0] $end
$var parameter 32 3 ACC_WIDTH $end
$var parameter 32 4 DATA_WIDTH $end
$var reg 32 5 accumulator [31:0] $end
$var reg 8 6 activation_out [7:0] $end
$var reg 32 7 psum_out [31:0] $end
$var reg 8 8 weight_out [7:0] $end
$upscope $end
$upscope $end
$scope begin COL[1] $end
$var parameter 2 9 col $end
$scope module pe_inst $end
$var wire 8 : activation_in [7:0] $end
$var wire 1 # clear_acc $end
$var wire 1 $ clk $end
$var wire 1 % enable $end
$var wire 1 & reset $end
$var wire 8 ; weight_in [7:0] $end
$var wire 16 < product [15:0] $end
$var parameter 32 = ACC_WIDTH $end
$var parameter 32 > DATA_WIDTH $end
$var reg 32 ? accumulator [31:0] $end
$var reg 8 @ activation_out [7:0] $end
$var reg 32 A psum_out [31:0] $end
$var reg 8 B weight_out [7:0] $end
$upscope $end
$upscope $end
$scope begin COL[2] $end
$var parameter 3 C col $end
$scope module pe_inst $end
$var wire 8 D activation_in [7:0] $end
$var wire 1 # clear_acc $end
$var wire 1 $ clk $end
$var wire 1 % enable $end
$var wire 1 & reset $end
$var wire 8 E weight_in [7:0] $end
$var wire 16 F product [15:0] $end
$var parameter 32 G ACC_WIDTH $end
$var parameter 32 H DATA_WIDTH $end
$var reg 32 I accumulator [31:0] $end
$var reg 8 J activation_out [7:0] $end
$var reg 32 K psum_out [31:0] $end
$var reg 8 L weight_out [7:0] $end
$upscope $end
$upscope $end
$scope begin COL[3] $end
$var parameter 3 M col $end
$scope module pe_inst $end
$var wire 8 N activation_in [7:0] $end
$var wire 1 # clear_acc $end
$var wire 1 $ clk $end
$var wire 1 % enable $end
$var wire 1 & reset $end
$var wire 8 O weight_in [7:0] $end
$var wire 16 P product [15:0] $end
$var parameter 32 Q ACC_WIDTH $end
$var parameter 32 R DATA_WIDTH $end
$var reg 32 S accumulator [31:0] $end
$var reg 8 T activation_out [7:0] $end
$var reg 32 U psum_out [31:0] $end
$var reg 8 V weight_out [7:0] $end
$upscope $end
$upscope $end
$upscope $end
$scope begin ROW[1] $end
$var parameter 2 W row $end
$scope begin COL[0] $end
$var parameter 2 X col $end
$scope module pe_inst $end
$var wire 8 Y activation_in [7:0] $end
$var wire 1 # clear_acc $end
$var wire 1 $ clk $end
$var wire 1 % enable $end
$var wire 1 & reset $end
$var wire 8 Z weight_in [7:0] $end
$var wire 16 [ product [15:0] $end
$var parameter 32 \ ACC_WIDTH $end
$var parameter 32 ] DATA_WIDTH $end
$var reg 32 ^ accumulator [31:0] $end
$var reg 8 _ activation_out [7:0] $end
$var reg 32 ` psum_out [31:0] $end
$var reg 8 a weight_out [7:0] $end
$upscope $end
$upscope $end
$scope begin COL[1] $end
$var parameter 2 b col $end
$scope module pe_inst $end
$var wire 8 c activation_in [7:0] $end
$var wire 1 # clear_acc $end
$var wire 1 $ clk $end
$var wire 1 % enable $end
$var wire 1 & reset $end
$var wire 8 d weight_in [7:0] $end
$var wire 16 e product [15:0] $end
$var parameter 32 f ACC_WIDTH $end
$var parameter 32 g DATA_WIDTH $end
$var reg 32 h accumulator [31:0] $end
$var reg 8 i activation_out [7:0] $end
$var reg 32 j psum_out [31:0] $end
$var reg 8 k weight_out [7:0] $end
$upscope $end
$upscope $end
$scope begin COL[2] $end
$var parameter 3 l col $end
$scope module pe_inst $end
$var wire 8 m activation_in [7:0] $end
$var wire 1 # clear_acc $end
$var wire 1 $ clk $end
$var wire 1 % enable $end
$var wire 1 & reset $end
$var wire 8 n weight_in [7:0] $end
$var wire 16 o product [15:0] $end
$var parameter 32 p ACC_WIDTH $end
$var parameter 32 q DATA_WIDTH $end
$var reg 32 r accumulator [31:0] $end
$var reg 8 s activation_out [7:0] $end
$var reg 32 t psum_out [31:0] $end
$var reg 8 u weight_out [7:0] $end
$upscope $end
$upscope $end
$scope begin COL[3] $end
$var parameter 3 v col $end
$scope module pe_inst $end
$var wire 8 w activation_in [7:0] $end
$var wire 1 # clear_acc $end
$var wire 1 $ clk $end
$var wire 1 % enable $end
$var wire 1 & reset $end
$var wire 8 x weight_in [7:0] $end
$var wire 16 y product [15:0] $end
$var parameter 32 z ACC_WIDTH $end
$var parameter 32 { DATA_WIDTH $end
$var reg 32 | accumulator [31:0] $end
$var reg 8 } activation_out [7:0] $end
$var reg 32 ~ psum_out [31:0] $end
$var reg 8 !" weight_out [7:0] $end
$upscope $end
$upscope $end
$upscope $end
$scope begin ROW[2] $end
$var parameter 3 "" row $end
$scope begin COL[0] $end
$var parameter 2 #" col $end
$scope module pe_inst $end
$var wire 8 $" activation_in [7:0] $end
$var wire 1 # clear_acc $end
$var wire 1 $ clk $end
$var wire 1 % enable $end
$var wire 1 & reset $end
$var wire 8 %" weight_in [7:0] $end
$var wire 16 &" product [15:0] $end
$var parameter 32 '" ACC_WIDTH $end
$var parameter 32 (" DATA_WIDTH $end
$var reg 32 )" accumulator [31:0] $end
$var reg 8 *" activation_out [7:0] $end
$var reg 32 +" psum_out [31:0] $end
$var reg 8 ," weight_out [7:0] $end
$upscope $end
$upscope $end
$scope begin COL[1] $end
$var parameter 2 -" col $end
$scope module pe_inst $end
$var wire 8 ." activation_in [7:0] $end
$var wire 1 # clear_acc $end
$var wire 1 $ clk $end
$var wire 1 % enable $end
$var wire 1 & reset $end
$var wire 8 /" weight_in [7:0] $end
$var wire 16 0" product [15:0] $end
$var parameter 32 1" ACC_WIDTH $end
$var parameter 32 2" DATA_WIDTH $end
$var reg 32 3" accumulator [31:0] $end
$var reg 8 4" activation_out [7:0] $end
$var reg 32 5" psum_out [31:0] $end
$var reg 8 6" weight_out [7:0] $end
$upscope $end
$upscope $end
$scope begin COL[2] $end
$var parameter 3 7" col $end
$scope module pe_inst $end
$var wire 8 8" activation_in [7:0] $end
$var wire 1 # clear_acc $end
$var wire 1 $ clk $end
$var wire 1 % enable $end
$var wire 1 & reset $end
$var wire 8 9" weight_in [7:0] $end
$var wire 16 :" product [15:0] $end
$var parameter 32 ;" ACC_WIDTH $end
$var parameter 32 <" DATA_WIDTH $end
$var reg 32 =" accumulator [31:0] $end
$var reg 8 >" activation_out [7:0] $end
$var reg 32 ?" psum_out [31:0] $end
$var reg 8 @" weight_out [7:0] $end
$upscope $end
$upscope $end
$scope begin COL[3] $end
$var parameter 3 A" col $end
$scope module pe_inst $end
$var wire 8 B" activation_in [7:0] $end
$var wire 1 # clear_acc $end
$var wire 1 $ clk $end
$var wire 1 % enable $end
$var wire 1 & reset $end
$var wire 8 C" weight_in [7:0] $end
$var wire 16 D" product [15:0] $end
$var parameter 32 E" ACC_WIDTH $end
$var parameter 32 F" DATA_WIDTH $end
$var reg 32 G" accumulator [31:0] $end
$var reg 8 H" activation_out [7:0] $end
$var reg 32 I" psum_out [31:0] $end
$var reg 8 J" weight_out [7:0] $end
$upscope $end
$upscope $end
$upscope $end
$scope begin ROW[3] $end
$var parameter 3 K" row $end
$scope begin COL[0] $end
$var parameter 2 L" col $end
$scope module pe_inst $end
$var wire 8 M" activation_in [7:0] $end
$var wire 1 # clear_acc $end
$var wire 1 $ clk $end
$var wire 1 % enable $end
$var wire 1 & reset $end
$var wire 8 N" weight_in [7:0] $end
$var wire 16 O" product [15:0] $end
$var parameter 32 P" ACC_WIDTH $end
$var parameter 32 Q" DATA_WIDTH $end
$var reg 32 R" accumulator [31:0] $end
$var reg 8 S" activation_out [7:0] $end
$var reg 32 T" psum_out [31:0] $end
$var reg 8 U" weight_out [7:0] $end
$upscope $end
$upscope $end
$scope begin COL[1] $end
$var parameter 2 V" col $end
$scope module pe_inst $end
$var wire 8 W" activation_in [7:0] $end
$var wire 1 # clear_acc $end
$var wire 1 $ clk $end
$var wire 1 % enable $end
$var wire 1 & reset $end
$var wire 8 X" weight_in [7:0] $end
$var wire 16 Y" product [15:0] $end
$var parameter 32 Z" ACC_WIDTH $end
$var parameter 32 [" DATA_WIDTH $end
$var reg 32 \" accumulator [31:0] $end
$var reg 8 ]" activation_out [7:0] $end
$var reg 32 ^" psum_out [31:0] $end
$var reg 8 _" weight_out [7:0] $end
$upscope $end
$upscope $end
$scope begin COL[2] $end
$var parameter 3 `" col $end
$scope module pe_inst $end
$var wire 8 a" activation_in [7:0] $end
$var wire 1 # clear_acc $end
$var wire 1 $ clk $end
$var wire 1 % enable $end
$var wire 1 & reset $end
$var wire 8 b" weight_in [7:0] $end
$var wire 16 c" product [15:0] $end
$var parameter 32 d" ACC_WIDTH $end
$var parameter 32 e" DATA_WIDTH $end
$var reg 32 f" accumulator [31:0] $end
$var reg 8 g" activation_out [7:0] $end
$var reg 32 h" psum_out [31:0] $end
$var reg 8 i" weight_out [7:0] $end
$upscope $end
$upscope $end
$scope begin COL[3] $end
$var parameter 3 j" col $end
$scope module pe_inst $end
$var wire 8 k" activation_in [7:0] $end
$var wire 1 # clear_acc $end
$var wire 1 $ clk $end
$var wire 1 % enable $end
$var wire 1 & reset $end
$var wire 8 l" weight_in [7:0] $end
$var wire 16 m" product [15:0] $end
$var parameter 32 n" ACC_WIDTH $end
$var parameter 32 o" DATA_WIDTH $end
$var reg 32 p" accumulator [31:0] $end
$var reg 8 q" activation_out [7:0] $end
$var reg 32 r" psum_out [31:0] $end
$var reg 8 s" weight_out [7:0] $end
$upscope $end
$upscope $end
$upscope $end
$scope begin WEIGHT_INPUT[0] $end
$var parameter 2 t" c $end
$upscope $end
$scope begin WEIGHT_INPUT[1] $end
$var parameter 2 u" c $end
$upscope $end
$scope begin WEIGHT_INPUT[2] $end
$var parameter 3 v" c $end
$upscope $end
$scope begin WEIGHT_INPUT[3] $end
$var parameter 3 w" c $end
$upscope $end
$upscope $end
$upscope $end
$enddefinitions $end
$comment Show the parameter values. $end
$dumpall
b11 w"
b10 v"
b1 u"
b0 t"
b1000 o"
b100000 n"
b11 j"
b1000 e"
b100000 d"
b10 `"
b1000 ["
b100000 Z"
b1 V"
b1000 Q"
b100000 P"
b0 L"
b11 K"
b1000 F"
b100000 E"
b11 A"
b1000 <"
b100000 ;"
b10 7"
b1000 2"
b100000 1"
b1 -"
b1000 ("
b100000 '"
b0 #"
b10 ""
b1000 {
b100000 z
b11 v
b1000 q
b100000 p
b10 l
b1000 g
b100000 f
b1 b
b1000 ]
b100000 \
b0 X
b1 W
b1000 R
b100000 Q
b11 M
b1000 H
b100000 G
b10 C
b1000 >
b100000 =
b1 9
b1000 4
b100000 3
b0 /
b0 .
b11 -
b10 ,
b1 +
b0 *
b1000 )
b100000 (
b1000 "
b100000 !
$end
#0
$dumpvars
bx s"
bx r"
bx q"
bx p"
bx m"
bx l"
bx k"
bx i"
bx h"
bx g"
bx f"
bx c"
bx b"
bx a"
bx _"
bx ^"
bx ]"
bx \"
bx Y"
bx X"
bx W"
bx U"
bx T"
bx S"
bx R"
bx O"
bx N"
b0 M"
bx J"
bx I"
bx H"
bx G"
bx D"
bx C"
bx B"
bx @"
bx ?"
bx >"
bx ="
bx :"
bx 9"
bx 8"
bx 6"
bx 5"
bx 4"
bx 3"
bx 0"
bx /"
bx ."
bx ,"
bx +"
bx *"
bx )"
bx &"
bx %"
b0 $"
bx !"
bx ~
bx }
bx |
bx y
bx x
bx w
bx u
bx t
bx s
bx r
bx o
bx n
bx m
bx k
bx j
bx i
bx h
bx e
bx d
bx c
bx a
bx `
bx _
bx ^
bx [
bx Z
b0 Y
bx V
bx U
bx T
bx S
bx P
b0 O
bx N
bx L
bx K
bx J
bx I
bx F
b0 E
bx D
bx B
bx A
bx @
bx ?
bx <
b0 ;
bx :
bx 8
bx 7
bx 6
bx 5
b0 2
b0 1
b0 0
b100 '
1&
0%
0$
0#
$end
#5000
b0 7
b0 5
b0 [
b0 8
b0 Z
b0 <
b0 6
b0 :
b0 A
b0 ?
b0 e
b0 B
b0 d
b0 F
b0 @
b0 D
b0 K
b0 I
b0 o
b0 L
b0 n
b0 P
b0 J
b0 N
b0 U
b0 S
b0 y
b0 V
b0 x
b0 T
b0 `
b0 ^
b0 &"
b0 a
b0 %"
b0 _
b0 c
b0 j
b0 h
b0 0"
b0 k
b0 /"
b0 i
b0 m
b0 t
b0 r
b0 :"
b0 u
b0 9"
b0 s
b0 w
b0 ~
b0 |
b0 D"
b0 !"
b0 C"
b0 }
b0 +"
b0 )"
b0 O"
b0 ,"
b0 N"
b0 *"
b0 ."
b0 5"
b0 3"
b0 Y"
b0 6"
b0 X"
b0 4"
b0 8"
b0 ?"
b0 ="
b0 c"
b0 @"
b0 b"
b0 >"
b0 B"
b0 I"
b0 G"
b0 m"
b0 J"
b0 l"
b0 H"
b0 T"
b0 R"
b0 U"
b0 S"
b0 W"
b0 ^"
b0 \"
b0 _"
b0 ]"
b0 a"
b0 h"
b0 f"
b0 i"
b0 g"
b0 k"
b0 r"
b0 p"
b0 s"
b0 q"
1$
#10000
0$
#15000
1$
#20000
0$
1#
0&
#25000
1$
#30000
0$
b111 ;
b101 1
0#
#35000
b111 B
b111 d
b101 8
b101 Z
1$
#40000
0$
b101 2
b1 0
1%
#45000
b101 5
b111 <
b1 6
b1 :
b101 a
b101 %"
b111 k
b111 /"
1$
#50000
0$
b1010 2
b10 0
#55000
b111 6"
b111 X"
b101 ,"
b101 N"
b111 ?
b1 @
b1 D
b101 7
b1111 5
b1110 <
b10 6
b10 :
1$
#60000
0$
b1111 [
b11 Y
b0 2
b0 0
#65000
b1111 7
b0 <
b0 6
b0 :
b111 A
b10101 ?
b10 @
b10 D
b1 J
b1 N
b1111 ^
b10101 e
b11 _
b11 c
b101 U"
b111 _"
1$
#70000
0$
b10100 [
b100 Y
#75000
b10101 h
b11 i
b11 m
b1111 `
b100011 ^
b11100 e
b100 _
b100 c
b1 T
b10 J
b10 N
b10101 A
b0 @
b0 D
1$
#80000
0$
b0 [
b0 Y
#85000
b0 J
b0 N
b10 T
b100011 `
b0 e
b0 _
b0 c
b10101 j
b110001 h
b100 i
b100 m
b11 s
b11 w
1$
#90000
0$
#95000
b11 }
b100 s
b100 w
b110001 j
b0 i
b0 m
b0 T
1$
#100000
0$
#105000
b0 s
b0 w
b100 }
1$
#110000
0$
#115000
b0 }
1$
#120000
0$
#125000
1$
#130000
0$
0%
