RTL/Day03/register8.v
module register8(
    input clk,
    input reset,
    input [7:0] d,
    output reg [7:0] q
);


always @(posedge clk)
begin

    if(reset)
        q <= 8'b00000000;

    else
        q <= d;

end


endmodule

Testbench/Day03/register8_tb.v
`timescale 1ns/1ps

module register8_tb;


reg clk;
reg reset;
reg [7:0] d;

wire [7:0] q;



register8 uut(
    .clk(clk),
    .reset(reset),
    .d(d),
    .q(q)
);



// Clock
initial begin

    clk = 0;

    forever #5 clk = ~clk;

end



// Test
initial begin

    $dumpfile("register8.vcd");
    $dumpvars(0,register8_tb);


    // Reset
    reset = 1;
    d = 8'hAA;


    #10;


    // Release reset
    reset = 0;


    #10;


    // Load new data
    d = 8'h55;


    #10;


    // Load another value
    d = 8'hFF;


    #10;


    $finish;

end


endmodule

Simulation/Day03/register8/register8.vcd
$date
	Sat Jul 18 22:53:35 2026
$end
$version
	Icarus Verilog
$end
$timescale
	1ps
$end
$scope module register8_tb $end
$var wire 8 ! q [7:0] $end
$var reg 1 " clk $end
$var reg 8 # d [7:0] $end
$var reg 1 $ reset $end
$scope module uut $end
$var wire 1 " clk $end
$var wire 8 % d [7:0] $end
$var wire 1 $ reset $end
$var reg 8 & q [7:0] $end
$upscope $end
$upscope $end
$enddefinitions $end
$comment Show the parameter values. $end
$dumpall
$end
#0
$dumpvars
bx &
b10101010 %
1$
b10101010 #
0"
bx !
$end
#5000
b0 !
b0 &
1"
#10000
0"
0$
#15000
b10101010 !
b10101010 &
1"
#20000
0"
b1010101 #
b1010101 %
#25000
b1010101 !
b1010101 &
1"
#30000
0"
b11111111 #
b11111111 %
#35000
b11111111 !
b11111111 &
1"
