RTL/Day11/pe_unit.v
module pe_unit #(
    parameter DATA_WIDTH = 8,
    parameter ACC_WIDTH  = 32
)(
    input clk,
    input rst,
    input enable,

    // Load weight control
    input load_weight,
    input [DATA_WIDTH-1:0] weight_in,

    // Activation data flow
    input [DATA_WIDTH-1:0] activation_in,
    output reg [DATA_WIDTH-1:0] activation_out,

    // Partial sum flow
    input [ACC_WIDTH-1:0] partial_sum_in,
    output reg [ACC_WIDTH-1:0] partial_sum_out
);


    // Weight storage
    reg [DATA_WIDTH-1:0] weight_reg;


    // Multiplication result
    wire [2*DATA_WIDTH-1:0] mult_result;


    assign mult_result = activation_in * weight_reg;



    always @(posedge clk) begin

        if(rst) begin

            weight_reg      <= 0;
            partial_sum_out <= 0;
            activation_out  <= 0;

        end


        else begin


            // Load weight phase
            if(load_weight) begin

                weight_reg <= weight_in;

            end



            // Computation phase
            if(enable) begin

                partial_sum_out <= 
                    partial_sum_in + mult_result;


                activation_out <= activation_in;

            end

        end

    end


endmodule

RTL/Day11/pe_chain.v
module pe_chain #(
    parameter NUM_PE = 4,
    parameter DATA_WIDTH = 8,
    parameter ACC_WIDTH = 32
)(
    input clk,
    input rst,
    input enable,

    // weight loading control
    input load_weight,

    // activation input
    input [DATA_WIDTH-1:0] activation_in,

    // weight array
    input [NUM_PE*DATA_WIDTH-1:0] weight_in,

    // final output
    output [ACC_WIDTH-1:0] result
);


    /*
        activation connection between PE

        PE0 -> PE1 -> PE2 -> PE3
    */

    wire [DATA_WIDTH-1:0] activation_wire [0:NUM_PE];


    /*
        partial sum connection

        PS0 -> PS1 -> PS2 -> PS3
    */

    wire [ACC_WIDTH-1:0] partial_sum_wire [0:NUM_PE];


    assign activation_wire[0] = activation_in;


    // First PE starts from zero
    assign partial_sum_wire[0] = {ACC_WIDTH{1'b0}};



    genvar i;

    generate

        for(i=0;i<NUM_PE;i=i+1)
        begin : PE_ARRAY


            pe_unit #(
                .DATA_WIDTH(DATA_WIDTH),
                .ACC_WIDTH(ACC_WIDTH)
            )
            pe_inst
            (

                .clk(clk),
                .rst(rst),
                .enable(enable),


                // weight control
                .load_weight(load_weight),


                /*
                    extract each PE weight

                    PE0:
                    weight_in[7:0]

                    PE1:
                    weight_in[15:8]

                */

                .weight_in(
                    weight_in[
                        i*DATA_WIDTH +:
                        DATA_WIDTH
                    ]
                ),


                // activation flow

                .activation_in(
                    activation_wire[i]
                ),

                .activation_out(
                    activation_wire[i+1]
                ),


                // partial sum flow

                .partial_sum_in(
                    partial_sum_wire[i]
                ),

                .partial_sum_out(
                    partial_sum_wire[i+1]
                )

            );


        end

    endgenerate



    assign result = partial_sum_wire[NUM_PE];


endmodule

Testbench/Day11/pe_chain_tb.v
`timescale 1ns/1ps


module pe_chain_tb;


parameter NUM_PE = 4;
parameter DATA_WIDTH = 8;
parameter ACC_WIDTH = 32;


reg clk;
reg rst;
reg enable;

reg load_weight;


reg [DATA_WIDTH-1:0] activation_in;


reg [NUM_PE*DATA_WIDTH-1:0] weight_in;


wire [ACC_WIDTH-1:0] result;



pe_chain #(
    .NUM_PE(NUM_PE),
    .DATA_WIDTH(DATA_WIDTH),
    .ACC_WIDTH(ACC_WIDTH)
)
dut
(
    .clk(clk),
    .rst(rst),
    .enable(enable),

    .load_weight(load_weight),

    .activation_in(activation_in),

    .weight_in(weight_in),

    .result(result)
);



always #5 clk = ~clk;



initial begin


    $dumpfile("Simulation/Day11/pe_chain.vcd");
    $dumpvars(0, pe_chain_tb);



    clk = 0;

    rst = 1;

    enable = 0;

    load_weight = 0;

    activation_in = 0;

    weight_in = 0;



    // reset

    #20;

    rst = 0;



    //---------------------------------
    // Load weights
    //---------------------------------

    load_weight = 1;


    /*
       PE0 = 2
       PE1 = 3
       PE2 = 4
       PE3 = 5

       注意：
       高位 -> PE3
       低位 -> PE0

    */

    weight_in = {
        8'd5,
        8'd4,
        8'd3,
        8'd2
    };


    #10;


    load_weight = 0;



    //---------------------------------
    // Start pipeline
    //---------------------------------

    enable = 1;


    activation_in = 8'd1;



    #60;



    $display("Final Result = %d", result);



    if(result == 14)

        $display("PE_CHAIN TEST PASS");

    else

        $display("PE_CHAIN TEST FAIL");



    $finish;


end


endmodule

Simulation/Day11/pe_chain.vcd
$date
	Sun Aug  2 10:39:57 2026
$end
$version
	Icarus Verilog
$end
$timescale
	1ps
$end
$scope module pe_chain_tb $end
$var wire 32 ! result [31:0] $end
$var parameter 32 " ACC_WIDTH $end
$var parameter 32 # DATA_WIDTH $end
$var parameter 32 $ NUM_PE $end
$var reg 8 % activation_in [7:0] $end
$var reg 1 & clk $end
$var reg 1 ' enable $end
$var reg 1 ( load_weight $end
$var reg 1 ) rst $end
$var reg 32 * weight_in [31:0] $end
$scope module dut $end
$var wire 8 + activation_in [7:0] $end
$var wire 1 & clk $end
$var wire 1 ' enable $end
$var wire 1 ( load_weight $end
$var wire 32 , result [31:0] $end
$var wire 1 ) rst $end
$var wire 32 - weight_in [31:0] $end
$var parameter 32 . ACC_WIDTH $end
$var parameter 32 / DATA_WIDTH $end
$var parameter 32 0 NUM_PE $end
$scope begin PE_ARRAY[0] $end
$var parameter 2 1 i $end
$scope module pe_inst $end
$var wire 8 2 activation_in [7:0] $end
$var wire 1 & clk $end
$var wire 1 ' enable $end
$var wire 1 ( load_weight $end
$var wire 32 3 partial_sum_in [31:0] $end
$var wire 1 ) rst $end
$var wire 8 4 weight_in [7:0] $end
$var wire 16 5 mult_result [15:0] $end
$var parameter 32 6 ACC_WIDTH $end
$var parameter 32 7 DATA_WIDTH $end
$var reg 8 8 activation_out [7:0] $end
$var reg 32 9 partial_sum_out [31:0] $end
$var reg 8 : weight_reg [7:0] $end
$upscope $end
$upscope $end
$scope begin PE_ARRAY[1] $end
$var parameter 2 ; i $end
$scope module pe_inst $end
$var wire 8 < activation_in [7:0] $end
$var wire 1 & clk $end
$var wire 1 ' enable $end
$var wire 1 ( load_weight $end
$var wire 32 = partial_sum_in [31:0] $end
$var wire 1 ) rst $end
$var wire 8 > weight_in [7:0] $end
$var wire 16 ? mult_result [15:0] $end
$var parameter 32 @ ACC_WIDTH $end
$var parameter 32 A DATA_WIDTH $end
$var reg 8 B activation_out [7:0] $end
$var reg 32 C partial_sum_out [31:0] $end
$var reg 8 D weight_reg [7:0] $end
$upscope $end
$upscope $end
$scope begin PE_ARRAY[2] $end
$var parameter 3 E i $end
$scope module pe_inst $end
$var wire 8 F activation_in [7:0] $end
$var wire 1 & clk $end
$var wire 1 ' enable $end
$var wire 1 ( load_weight $end
$var wire 32 G partial_sum_in [31:0] $end
$var wire 1 ) rst $end
$var wire 8 H weight_in [7:0] $end
$var wire 16 I mult_result [15:0] $end
$var parameter 32 J ACC_WIDTH $end
$var parameter 32 K DATA_WIDTH $end
$var reg 8 L activation_out [7:0] $end
$var reg 32 M partial_sum_out [31:0] $end
$var reg 8 N weight_reg [7:0] $end
$upscope $end
$upscope $end
$scope begin PE_ARRAY[3] $end
$var parameter 3 O i $end
$scope module pe_inst $end
$var wire 8 P activation_in [7:0] $end
$var wire 1 & clk $end
$var wire 1 ' enable $end
$var wire 1 ( load_weight $end
$var wire 32 Q partial_sum_in [31:0] $end
$var wire 1 ) rst $end
$var wire 8 R weight_in [7:0] $end
$var wire 16 S mult_result [15:0] $end
$var parameter 32 T ACC_WIDTH $end
$var parameter 32 U DATA_WIDTH $end
$var reg 8 V activation_out [7:0] $end
$var reg 32 W partial_sum_out [31:0] $end
$var reg 8 X weight_reg [7:0] $end
$upscope $end
$upscope $end
$upscope $end
$upscope $end
$enddefinitions $end
$comment Show the parameter values. $end
$dumpall
b1000 U
b100000 T
b11 O
b1000 K
b100000 J
b10 E
b1000 A
b100000 @
b1 ;
b1000 7
b100000 6
b0 1
b100 0
b1000 /
b100000 .
b100 $
b1000 #
b100000 "
$end
#0
$dumpvars
bx X
bx W
bx V
bx S
b0 R
bx Q
bx P
bx N
bx M
bx L
bx I
b0 H
bx G
bx F
bx D
bx C
bx B
bx ?
b0 >
bx =
bx <
bx :
bx 9
bx 8
bx 5
b0 4
b0 3
b0 2
b0 -
bx ,
b0 +
b0 *
1)
0(
0'
0&
b0 %
bx !
$end
#5000
b0 ?
b0 8
b0 <
b0 9
b0 =
b0 5
b0 :
b0 I
b0 B
b0 F
b0 C
b0 G
b0 D
b0 S
b0 L
b0 P
b0 M
b0 Q
b0 N
b0 V
b0 !
b0 ,
b0 W
b0 X
1&
#10000
0&
#15000
1&
#20000
b10 4
b11 >
b100 H
b101 R
0&
b101000001000000001100000010 *
b101000001000000001100000010 -
1(
0)
#25000
b10 :
b11 D
b100 N
b101 X
1&
#30000
0&
b10 5
b1 2
b1 %
b1 +
1'
0(
#35000
b11 ?
b1 8
b1 <
b10 9
b10 =
1&
#40000
0&
#45000
b100 I
b1 B
b1 F
b101 C
b101 G
1&
#50000
0&
#55000
b101 S
b1 L
b1 P
b1001 M
b1001 Q
1&
#60000
0&
#65000
b1 V
b1110 !
b1110 ,
b1110 W
1&
