RTL/Day11/pe_unit.v
module pe_unit #(
    parameter DATA_WIDTH = 8,
    parameter ACC_WIDTH  = 32
)(
    input clk,
    input rst,
    input enable,

    // Load weight control
    input load_weight,
    input [DATA_WIDTH-1:0] weight_in,

    // Activation data flow
    input [DATA_WIDTH-1:0] activation_in,
    output reg [DATA_WIDTH-1:0] activation_out,

    // Partial sum flow
    input [ACC_WIDTH-1:0] partial_sum_in,
    output reg [ACC_WIDTH-1:0] partial_sum_out
);


    // Weight storage
    reg [DATA_WIDTH-1:0] weight_reg;


    // Multiplication result
    wire [2*DATA_WIDTH-1:0] mult_result;


    assign mult_result = activation_in * weight_reg;



    always @(posedge clk) begin

        if(rst) begin

            weight_reg      <= 0;
            partial_sum_out <= 0;
            activation_out  <= 0;

        end


        else begin


            // Load weight phase
            if(load_weight) begin

                weight_reg <= weight_in;

            end



            // Computation phase
            if(enable) begin

                partial_sum_out <= 
                    partial_sum_in + mult_result;


                activation_out <= activation_in;

            end

        end

    end


endmodule

Testbench/Day11/pe_unit_tb.v
`timescale 1ns/1ps


module pe_unit_tb;


parameter DATA_WIDTH = 8;
parameter ACC_WIDTH  = 32;


reg clk;
reg rst;
reg enable;


reg load_weight;

reg [DATA_WIDTH-1:0] weight_in;


reg [DATA_WIDTH-1:0] activation_in;

wire [DATA_WIDTH-1:0] activation_out;


reg [ACC_WIDTH-1:0] partial_sum_in;

wire [ACC_WIDTH-1:0] partial_sum_out;



// DUT

pe_unit #(
    .DATA_WIDTH(DATA_WIDTH),
    .ACC_WIDTH(ACC_WIDTH)
)
dut
(

    .clk(clk),

    .rst(rst),

    .enable(enable),


    .load_weight(load_weight),

    .weight_in(weight_in),


    .activation_in(activation_in),

    .activation_out(activation_out),


    .partial_sum_in(partial_sum_in),

    .partial_sum_out(partial_sum_out)

);




// clock

always #5 clk = ~clk;



initial begin


    $dumpfile("Simulation/Day11/pe_unit.vcd");
    $dumpvars(0, pe_unit_tb);



    clk = 0;

    rst = 1;

    enable = 0;

    load_weight = 0;


    weight_in = 0;

    activation_in = 0;

    partial_sum_in = 0;



    // reset

    #20;

    rst = 0;



    //---------------------
    // Load weight
    //---------------------

    load_weight = 1;

    weight_in = 8'd3;


    #10;


    load_weight = 0;



    //---------------------
    // Test 1
    //---------------------

    enable = 1;


    activation_in = 8'd2;

    partial_sum_in = 32'd0;


    #10;


    if(partial_sum_out == 6)

        $display("TEST1 PASS");

    else

        $display("TEST1 FAIL result=%d",
                  partial_sum_out);



    //---------------------
    // Test 2
    //---------------------


    activation_in = 8'd4;

    partial_sum_in = partial_sum_out;


    #10;


    if(partial_sum_out == 18)

        $display("TEST2 PASS");

    else

        $display("TEST2 FAIL result=%d",
                  partial_sum_out);



    $finish;


end


endmodule

Simulation/Day11/pe_unit.vcd
$date
	Sun Aug  2 10:37:01 2026
$end
$version
	Icarus Verilog
$end
$timescale
	1ps
$end
$scope module pe_unit_tb $end
$var wire 32 ! partial_sum_out [31:0] $end
$var wire 8 " activation_out [7:0] $end
$var parameter 32 # ACC_WIDTH $end
$var parameter 32 $ DATA_WIDTH $end
$var reg 8 % activation_in [7:0] $end
$var reg 1 & clk $end
$var reg 1 ' enable $end
$var reg 1 ( load_weight $end
$var reg 32 ) partial_sum_in [31:0] $end
$var reg 1 * rst $end
$var reg 8 + weight_in [7:0] $end
$scope module dut $end
$var wire 8 , activation_in [7:0] $end
$var wire 1 & clk $end
$var wire 1 ' enable $end
$var wire 1 ( load_weight $end
$var wire 32 - partial_sum_in [31:0] $end
$var wire 1 * rst $end
$var wire 8 . weight_in [7:0] $end
$var wire 16 / mult_result [15:0] $end
$var parameter 32 0 ACC_WIDTH $end
$var parameter 32 1 DATA_WIDTH $end
$var reg 8 2 activation_out [7:0] $end
$var reg 32 3 partial_sum_out [31:0] $end
$var reg 8 4 weight_reg [7:0] $end
$upscope $end
$upscope $end
$enddefinitions $end
$comment Show the parameter values. $end
$dumpall
b1000 1
b100000 0
b1000 $
b100000 #
$end
#0
$dumpvars
bx 4
bx 3
bx 2
bx /
b0 .
b0 -
b0 ,
b0 +
1*
b0 )
0(
0'
0&
b0 %
bx "
bx !
$end
#5000
b0 "
b0 2
b0 !
b0 3
b0 /
b0 4
1&
#10000
0&
#15000
1&
#20000
0&
b11 +
b11 .
1(
0*
#25000
b11 4
1&
#30000
0&
b110 /
b10 %
b10 ,
1'
0(
#35000
b10 "
b10 2
b110 !
b110 3
1&
#40000
0&
b110 )
b110 -
b1100 /
b100 %
b100 ,
#45000
b100 "
b100 2
b10010 !
b10010 3
1&
