RTL/Day08/processing_element.v
module processing_element #(
    parameter DATA_WIDTH = 8,
    parameter ACC_WIDTH  = 32
)
(
    input clk,
    input reset,

    input signed [DATA_WIDTH-1:0] activation,
    input signed [DATA_WIDTH-1:0] weight,

    output reg signed [ACC_WIDTH-1:0] partial_sum
);


wire signed [2*DATA_WIDTH-1:0] product;


assign product = activation * weight;


always @(posedge clk)
begin

    if(reset)

        partial_sum <= 0;

    else

        partial_sum <= partial_sum + product;

end


endmodule

Testbench/Day08/processing_element_tb.v
`timescale 1ns/1ps

module processing_element_tb;


reg clk;
reg reset;

reg signed [7:0] activation;
reg signed [7:0] weight;


wire signed [31:0] partial_sum;



processing_element dut(

    .clk(clk),
    .reset(reset),

    .activation(activation),
    .weight(weight),

    .partial_sum(partial_sum)

);



always #5 clk = ~clk;



initial begin

    $dumpfile("Simulation/Day08/processing_element.vcd");
    $dumpvars(0, processing_element_tb);



    clk = 0;
    reset = 1;

    activation = 0;
    weight = 0;


    #10;


    reset = 0;


    // Test 1
    activation = 8'd2;
    weight = 8'd3;
    #10;
if(partial_sum != 32'd6)
    $display("TEST1 FAIL");
else
    $display("TEST1 PASS");

    // Test 2
    activation = 8'd4;
    weight = 8'd5;
activation = 8'd4;
weight = 8'd5;

#10;

if(partial_sum != 32'd26)
    $display("TEST2 FAIL");
else
    $display("TEST2 PASS");
    #10;


    // Test 3
    activation = 8'd10;
    weight = 8'd2;
if(partial_sum != 32'd46)
    $display("TEST3 FAIL");
else
    $display("TEST3 PASS");
    #10;


    $finish;


end


endmodule

Simulation/Day08/processing_element.vcd
$date
	Thu Jul 30 21:16:41 2026
$end
$version
	Icarus Verilog
$end
$timescale
	1ps
$end
$scope module processing_element_tb $end
$var wire 32 ! partial_sum [31:0] $end
$var reg 8 " activation [7:0] $end
$var reg 1 # clk $end
$var reg 1 $ reset $end
$var reg 8 % weight [7:0] $end
$scope module dut $end
$var wire 8 & activation [7:0] $end
$var wire 1 # clk $end
$var wire 1 $ reset $end
$var wire 8 ' weight [7:0] $end
$var wire 16 ( product [15:0] $end
$var parameter 32 ) ACC_WIDTH $end
$var parameter 32 * DATA_WIDTH $end
$var reg 32 + partial_sum [31:0] $end
$upscope $end
$upscope $end
$enddefinitions $end
$comment Show the parameter values. $end
$dumpall
b1000 *
b100000 )
$end
#0
$dumpvars
bx +
b0 (
b0 '
b0 &
b0 %
1$
0#
b0 "
bx !
$end
#5000
b0 !
b0 +
1#
#10000
0#
b110 (
b11 %
b11 '
b10 "
b10 &
0$
#15000
b110 !
b110 +
1#
#20000
0#
b101 %
b101 '
b10100 (
b100 "
b100 &
#25000
b11010 !
b11010 +
1#
#30000
0#
#35000
b101110 !
b101110 +
1#
#40000
0#
b10 %
b10 '
b10100 (
b1010 "
b1010 &
#45000
b1000010 !
b1000010 +
1#
