RTL/Day06/register_bank.v
module register_bank
#(
    parameter DATA_WIDTH = 16,
    parameter DEPTH = 8,
    parameter ADDR_WIDTH = $clog2(DEPTH)
)
(
    input clk,
    input reset,

    input write_enable,

    input [ADDR_WIDTH-1:0] write_addr,

    input [DATA_WIDTH-1:0] write_data,

    input [ADDR_WIDTH-1:0] read_addr,

    output [DATA_WIDTH-1:0] read_data
);


reg [DATA_WIDTH-1:0] mem [0:DEPTH-1];



always @(posedge clk)
begin

    if (reset)
    begin

    end

    else if (write_enable)
    begin
        mem[write_addr] <= write_data;
    end

end



assign read_data = mem[read_addr];


endmodule

Testbench/Day06/register_bank_tb.v
`timescale 1ns/1ps


module register_bank_tb;


////////////////////////////////////////////////
// IP Configuration
////////////////////////////////////////////////

parameter DATA_WIDTH = 16;
parameter DEPTH = 8;

localparam ADDR_WIDTH = $clog2(DEPTH);



////////////////////////////////////////////////
// Testbench Signals
////////////////////////////////////////////////

reg clk;

reg reset;


reg write_enable;

reg [ADDR_WIDTH-1:0] write_addr;

reg [DATA_WIDTH-1:0] write_data;


reg [ADDR_WIDTH-1:0] read_addr;


wire [DATA_WIDTH-1:0] read_data;



////////////////////////////////////////////////
// Expected Memory
// Used for self-checking
////////////////////////////////////////////////

reg [DATA_WIDTH-1:0] expected [0:DEPTH-1];



integer i;

integer errors;



////////////////////////////////////////////////
// DUT
////////////////////////////////////////////////

register_bank
#(
    .DATA_WIDTH(DATA_WIDTH),
    .DEPTH(DEPTH)
)
dut
(
    .clk(clk),

    .reset(reset),

    .write_enable(write_enable),

    .write_addr(write_addr),

    .write_data(write_data),

    .read_addr(read_addr),

    .read_data(read_data)
);



////////////////////////////////////////////////
// Clock
////////////////////////////////////////////////

always #5 clk = ~clk;



////////////////////////////////////////////////
// Test Sequence
////////////////////////////////////////////////

initial
begin


    //////////////////////////////////////////////////
    // Waveform
    //////////////////////////////////////////////////

    $dumpfile("Simulation/Day06/register_bank.vcd");

    $dumpvars(0, register_bank_tb);



    //////////////////////////////////////////////////
    // Initialize
    //////////////////////////////////////////////////

    clk = 0;

    reset = 1;

    write_enable = 0;

    write_addr = 0;

    write_data = 0;

    read_addr = 0;

    errors = 0;



    //////////////////////////////////////////////////
    // Reset Release
    //////////////////////////////////////////////////

    #10;

    reset = 0;



    //////////////////////////////////////////////////
    // Write Test
    //////////////////////////////////////////////////

    #10;


    write_enable = 1;


    for(i=0;i<DEPTH;i=i+1)
    begin

        write_addr = i;

        write_data = i + 1;


        // Save expected result

        expected[i] = write_data;


        #10;

    end



    write_enable = 0;



    //////////////////////////////////////////////////
    // Read And Check
    //////////////////////////////////////////////////

    #10;


    for(i=0;i<DEPTH;i=i+1)
    begin


        read_addr = i;


        #5;


        if(read_data == expected[i])
        begin

            $display(
            "PASS : addr=%0d expected=%h actual=%h",
            read_addr,
            expected[i],
            read_data
            );

        end


        else
        begin

            $display(
            "FAIL : addr=%0d expected=%h actual=%h",
            read_addr,
            expected[i],
            read_data
            );


            errors = errors + 1;

        end


    end



    //////////////////////////////////////////////////
    // Summary
    //////////////////////////////////////////////////

    #10;


    if(errors == 0)
    begin

        $display("====================");
        $display("TEST PASSED");
        $display("====================");

    end


    else
    begin

        $display("====================");
        $display("TEST FAILED");
        $display("ERROR COUNT = %0d", errors);
        $display("====================");

    end



    #20;

    $finish;


end


endmodule

Simulation/Day06/register_bank.vcd
$date
	Tue Jul 28 21:05:24 2026
$end
$version
	Icarus Verilog
$end
$timescale
	1ps
$end
$scope module register_bank_tb $end
$var wire 16 ! read_data [15:0] $end
$var parameter 32 " ADDR_WIDTH $end
$var parameter 32 # DATA_WIDTH $end
$var parameter 32 $ DEPTH $end
$var reg 1 % clk $end
$var reg 3 & read_addr [2:0] $end
$var reg 1 ' reset $end
$var reg 3 ( write_addr [2:0] $end
$var reg 16 ) write_data [15:0] $end
$var reg 1 * write_enable $end
$var integer 32 + errors [31:0] $end
$var integer 32 , i [31:0] $end
$scope module dut $end
$var wire 1 % clk $end
$var wire 3 - read_addr [2:0] $end
$var wire 16 . read_data [15:0] $end
$var wire 1 ' reset $end
$var wire 3 / write_addr [2:0] $end
$var wire 16 0 write_data [15:0] $end
$var wire 1 * write_enable $end
$var parameter 32 1 ADDR_WIDTH $end
$var parameter 32 2 DATA_WIDTH $end
$var parameter 32 3 DEPTH $end
$upscope $end
$upscope $end
$enddefinitions $end
$comment Show the parameter values. $end
$dumpall
b1000 3
b10000 2
b11 1
b1000 $
b10000 #
b11 "
$end
#0
$dumpvars
b0 0
b0 /
bx .
b0 -
bx ,
b0 +
0*
b0 )
b0 (
1'
b0 &
0%
bx !
$end
#5000
1%
#10000
0%
0'
#15000
1%
#20000
0%
b1 )
b1 0
b0 ,
1*
#25000
b1 !
b1 .
1%
#30000
0%
b10 )
b10 0
b1 (
b1 /
b1 ,
#35000
1%
#40000
0%
b11 )
b11 0
b10 (
b10 /
b10 ,
#45000
1%
#50000
0%
b100 )
b100 0
b11 (
b11 /
b11 ,
#55000
1%
#60000
0%
b101 )
b101 0
b100 (
b100 /
b100 ,
#65000
1%
#70000
0%
b110 )
b110 0
b101 (
b101 /
b101 ,
#75000
1%
#80000
0%
b111 )
b111 0
b110 (
b110 /
b110 ,
#85000
1%
#90000
0%
b1000 )
b1000 0
b111 (
b111 /
b111 ,
#95000
1%
#100000
0%
0*
b1000 ,
#105000
1%
#110000
0%
b0 ,
#115000
1%
b10 !
b10 .
b1 &
b1 -
b1 ,
#120000
0%
b11 !
b11 .
b10 &
b10 -
b10 ,
#125000
1%
b100 !
b100 .
b11 &
b11 -
b11 ,
#130000
0%
b101 !
b101 .
b100 &
b100 -
b100 ,
#135000
1%
b110 !
b110 .
b101 &
b101 -
b101 ,
#140000
0%
b111 !
b111 .
b110 &
b110 -
b110 ,
#145000
1%
b1000 !
b1000 .
b111 &
b111 -
b111 ,
#150000
0%
b1000 ,
